{
  "ID": 19243,
  "事業ID": 8303,
  "公開年度": 2018,
  "事業名": "国内石油天然ガスに係る地質調査・メタンハイドレートの研究開発等事業",
  "開始年度": 2017,
  "終了年度": null,
  "府省庁": "経済産業省",
  "事業番号1": null,
  "事業番号2": "0208",
  "事業番号3": null,
  "担当部局庁": "資源エネルギー庁　資源・燃料部",
  "担当課室": "石油・天然ガス課",
  "作成責任者": "課長　佐々木　雅人",
  "会計区分": [
    "エネルギー対策特別会計エネルギー需給勘定"
  ],
  "事業目的": "　日本周辺海域に一定の資源量が期待される在来・非在来型の石油・天然ガスを安定的なエネルギー資源として利用可能とするため、エネルギー基本計画等に基づき、資源量調査や技術開発等を実施する。",
  "事業概要": "　日本周辺海域の未探鉱地域等において、三次元物理探査船により、石油・天然ガスのポテンシャルを把握するための調査を行うとともに、調査データの公開を通じて、我が国企業による探鉱開発活動を促進する。また、これまでの調査結果に基づき、石油・天然ガスの存在や地質・地質構造を具体的に確認するための基礎試錐（掘削調査）を実施するとともに、民間企業が自ら実施する掘削調査に対し支援を行う。\n　日本周辺海域に相当量の賦存が期待されるメタンハイドレートについて、我が国のエネルギー安定供給に資する重要なエネルギー資源として、将来の商業生産を可能とするために必要な技術開発を行う。",
  "実施方法": [
    "委託・請負",
    "補助"
  ],
  "主要施策": [
    "海洋政策",
    "科学技術・イノベーション",
    "国土強靱化施策"
  ],
  "予算": [
    {
      "年度": 2015,
      "当初予算": 0.0,
      "補正予算": 0.0,
      "前年度から繰越し": 0.0,
      "翌年度へ繰越し": 0.0,
      "予備費等": 0.0,
      "予算計": 0.0,
      "執行額": 0.0
    },
    {
      "年度": 2016,
      "当初予算": 0.0,
      "補正予算": 0.0,
      "前年度から繰越し": 0.0,
      "翌年度へ繰越し": 0.0,
      "予備費等": 0.0,
      "予算計": 0.0,
      "執行額": 0.0
    },
    {
      "年度": 2017,
      "当初予算": 24200.0,
      "補正予算": 0.0,
      "前年度から繰越し": 0.0,
      "翌年度へ繰越し": -11291.0,
      "予備費等": 0.0,
      "予算計": 12909.0,
      "執行額": 12409.0
    },
    {
      "年度": 2018,
      "当初予算": 22690.0,
      "補正予算": 0.0,
      "前年度から繰越し": 11291.0,
      "翌年度へ繰越し": 0.0,
      "予備費等": 0.0,
      "予算計": 33981.0
    },
    {
      "年度": 2019,
      "要求額": 28150.0
    }
  ],
  "支出先": [
    {
      "年度": 2017,
      "グループ": "A",
      "番号": 1,
      "支出先名": "独立行政法人石油天然ガス・金属鉱物資源機構",
      "法人番号": "4010405009573",
      "業務概要": "海上基礎物理探査及び全体管理",
      "支出額": 8300.0
    },
    {
      "年度": 2017,
      "グループ": "B",
      "番号": 1,
      "支出先名": "石油資源開発株式会社",
      "法人番号": "3010001108219",
      "業務概要": "海上基礎試錐",
      "支出額": 0.0
    },
    {
      "年度": 2017,
      "グループ": "C",
      "番号": 1,
      "支出先名": "独立行政法人石油天然ガス・金属鉱物資源機構",
      "法人番号": "4010405009573",
      "業務概要": "海上基礎物理探査及び全体管理",
      "支出額": 5.0
    },
    {
      "年度": 2017,
      "グループ": "D",
      "番号": 1,
      "支出先名": "独立行政法人石油天然ガス・金属鉱物資源機構",
      "法人番号": "4010405009573",
      "業務概要": "メタンハイドレートコンソーシアム事業全体に関する総括業務やフィールド開発技術、資源量評価、環境影響表に関する研究開発等",
      "支出額": 2800.0
    },
    {
      "年度": 2017,
      "グループ": "E",
      "番号": 1,
      "支出先名": "国立研究開発法人産業技術総合研究所",
      "法人番号": "7010005005425",
      "業務概要": "メタンハイドレートの生産手法開発、表層型メタンハイドレート回収技術調査等",
      "支出額": 1245.0
    },
    {
      "年度": 2017,
      "グループ": "F",
      "番号": 1,
      "支出先名": "みずほリサーチ＆テクノロジーズ株式会社",
      "法人番号": "9010001027685",
      "業務概要": "メタンハイドレートの今後の研究の在り方に関する調査",
      "支出額": 24.0
    },
    {
      "年度": 2017,
      "グループ": "G",
      "番号": 1,
      "支出先名": "三次元物理探査船運航管理共同企業体",
      "法人番号": null,
      "業務概要": "三次元物理探査船の運航管理等",
      "支出額": 2589.0
    },
    {
      "年度": 2017,
      "グループ": "H",
      "番号": 1,
      "支出先名": "ＰＧＳ　Ｇｅｏｐｈｙｓｉｃａｌ　ＡＳ",
      "法人番号": "2700150002392",
      "業務概要": "物理探査に係る技術移転・操業支援等",
      "支出額": 3947.0
    },
    {
      "年度": 2017,
      "グループ": "I",
      "番号": 1,
      "支出先名": "日本メタンハイドレート調査株式会社",
      "法人番号": "2010001163280",
      "業務概要": "第2回海洋産出試験ｵﾍﾟﾚｰﾀ業務（Stage4）",
      "支出額": 1613.0
    },
    {
      "年度": 2017,
      "グループ": "I",
      "番号": 2,
      "支出先名": "株式会社地球科学総合研究所",
      "法人番号": "7010001004868",
      "業務概要": "第2回海洋産出試験に係る物理探査ﾓﾆﾀﾘﾝｸﾞ",
      "支出額": 210.0
    },
    {
      "年度": 2017,
      "グループ": "I",
      "番号": 3,
      "支出先名": "シュルンベルジェ株式会社",
      "法人番号": "3021001012649",
      "業務概要": "ﾓﾆﾀﾘﾝｸﾞ装置設計・製造・ﾃﾞｰﾀ取得・解析",
      "支出額": 148.0
    },
    {
      "年度": 2017,
      "グループ": "I",
      "番号": 4,
      "支出先名": "株式会社日本海洋生物研究所",
      "法人番号": "9010701007648",
      "業務概要": "海域環境調査計画策定・調査実施・ﾃﾞｰﾀ解析・解釈",
      "支出額": 138.0
    },
    {
      "年度": 2017,
      "グループ": "I",
      "番号": 5,
      "支出先名": "東洋エンジニアリング株式会社",
      "法人番号": "9010001024113",
      "業務概要": "長期陸上産出試験の試験ｼｽﾃﾑ計画策定支援業務",
      "支出額": 81.0
    },
    {
      "年度": 2017,
      "グループ": "I",
      "番号": 6,
      "支出先名": "日本メタンハイドレート調査株式会社",
      "法人番号": "2010001163280",
      "業務概要": "海洋開発ｼｽﾃﾑの検討に係る支援作業",
      "支出額": 34.0
    },
    {
      "年度": 2017,
      "グループ": "I",
      "番号": 7,
      "支出先名": "一般財団法人エンジニアリング協会",
      "法人番号": "1010405009436",
      "業務概要": "海洋生態系への影響評価のための基礎研究",
      "支出額": 13.0
    },
    {
      "年度": 2017,
      "グループ": "I",
      "番号": 8,
      "支出先名": "Petrotechnical Resources of Alaska ",
      "法人番号": null,
      "業務概要": "長期陸上産出試験に向けての計画検討に係る支援作業",
      "支出額": 10.0
    },
    {
      "年度": 2017,
      "グループ": "I",
      "番号": 9,
      "支出先名": "シュルンベルジェ株式会社",
      "法人番号": "3021001012649",
      "業務概要": "ﾒﾀﾝﾊｲﾄﾞﾚｰﾄｼｽﾃﾑﾓﾃﾞﾘﾝｸﾞｽﾀﾃﾞィー結果の技術評価",
      "支出額": 5.0
    },
    {
      "年度": 2017,
      "グループ": "I",
      "番号": 10,
      "支出先名": "Regents of the University of Minnesota",
      "法人番号": null,
      "業務概要": "沈殿堆積盆における実験層序学研究",
      "支出額": 3.0
    },
    {
      "年度": 2017,
      "グループ": "J",
      "番号": 1,
      "支出先名": "株式会社三井Ｅ＆Ｓホールディングス",
      "法人番号": "9010001034946",
      "業務概要": "坑井内流動の実験的解析と坑底圧制御技術の開発",
      "支出額": 37.0
    },
    {
      "年度": 2017,
      "グループ": "J",
      "番号": 2,
      "支出先名": "株式会社三井Ｅ＆Ｓホールディングス",
      "法人番号": "9010001034946",
      "業務概要": "表層型メタンハイドレート回収技術開発に関わる調査研究（広範囲鉛直掘削法による表層型メタンハイドレート回収の基礎的検討） ",
      "支出額": 17.0
    },
    {
      "年度": 2017,
      "グループ": "J",
      "番号": 3,
      "支出先名": "石油資源開発株式会社",
      "法人番号": "3010001108219",
      "業務概要": "表層型メタンハイドレート回収技術開発に関わる調査研究（閉鎖環境を前提としたメタンハイドレート回収技術の研究）",
      "支出額": 21.0
    },
    {
      "年度": 2017,
      "グループ": "J",
      "番号": 4,
      "支出先名": "鹿島建設株式会社",
      "法人番号": "8010401006744",
      "業務概要": "細粒砂移流による貯留層障害対策技術の開発",
      "支出額": 19.0
    },
    {
      "年度": 2017,
      "グループ": "J",
      "番号": 5,
      "支出先名": "清水建設株式会社",
      "法人番号": "1010401013565",
      "業務概要": "遠心載荷手法による海底地すべり可能性に対する検討",
      "支出額": 9.0
    },
    {
      "年度": 2017,
      "グループ": "J",
      "番号": 6,
      "支出先名": "清水建設株式会社",
      "法人番号": "1010401013565",
      "業務概要": "表層型メタンハイドレート回収技術開発に関わる調査研究（採掘機と分離装置を用いた回収システムの検討）",
      "支出額": 5.0
    },
    {
      "年度": 2017,
      "グループ": "J",
      "番号": 7,
      "支出先名": "清水建設株式会社",
      "法人番号": "1010401013565",
      "業務概要": "表層型メタンハイドレート回収技術開発に関わる調査研究（広範囲鉛直掘削法による表層型メタンハイドレート回収の基礎的検討）",
      "支出額": 4.0
    },
    {
      "年度": 2017,
      "グループ": "J",
      "番号": 8,
      "支出先名": "国立大学法人東京大学",
      "法人番号": "5010005007398",
      "業務概要": "坑井周辺物質流動解析と実用化生産シミュレータへの適用",
      "支出額": 16.0
    },
    {
      "年度": 2017,
      "グループ": "J",
      "番号": 9,
      "支出先名": "国立大学法人鳥取大学",
      "法人番号": "4270005002614",
      "業務概要": "表層型メタンハイドレート回収技術開発に関わる調査研究（表層型メタンハイドレートを対象とした減圧・加熱併用法に関する調査・検討）",
      "支出額": 13.0
    },
    {
      "年度": 2017,
      "グループ": "J",
      "番号": 10,
      "支出先名": "国立研究開発法人海上・港湾・航空技術研究所",
      "法人番号": "5012405001732",
      "業務概要": "表層型メタンハイドレート回収技術開発に関わる調査研究（採掘機と分離装置を用いた回収システムの検討）",
      "支出額": 10.0
    },
    {
      "年度": 2017,
      "グループ": "J",
      "番号": 11,
      "支出先名": "太陽工業株式会社",
      "法人番号": "9120001056632",
      "業務概要": "表層型メタンハイドレート回収技術開発に関わる調査研究（ドーム状の膜構造物利用による回収技術の検討）",
      "支出額": 9.0
    },
    {
      "年度": 2017,
      "グループ": "J",
      "番号": 12,
      "支出先名": "一般財団法人電力中央研究所",
      "法人番号": "4010005018545",
      "業務概要": "炭酸ガススラリー圧入加熱法の実フィールドへの適用性の検討",
      "支出額": 9.0
    },
    {
      "年度": 2017,
      "グループ": "J",
      "番号": 13,
      "支出先名": "西日本技術開発株式会社",
      "法人番号": "6290001017728",
      "業務概要": "地層変形シミュレータの改良・機能追加",
      "支出額": 9.0
    },
    {
      "年度": 2017,
      "グループ": "J",
      "番号": 14,
      "支出先名": "日本オイルエンジニアリング株式会社",
      "法人番号": "3010001061871",
      "業務概要": "実用化生産シミュレータの改良・機能強化",
      "支出額": 9.0
    },
    {
      "年度": 2017,
      "グループ": "K",
      "番号": 1,
      "支出先名": "深田サルベージ建設株式会社",
      "法人番号": "9120001029720",
      "業務概要": "メタンハイドレート分布域の海洋電磁探査",
      "支出額": 495.0
    },
    {
      "年度": 2017,
      "グループ": "K",
      "番号": 2,
      "支出先名": "日本オイルエンジニアリング株式会社",
      "法人番号": "3010001061871",
      "業務概要": "MH濃集帯の貯留層モデル開発と生産挙動予測・検証作業及び商業生産の生産性評価作業",
      "支出額": 65.0
    },
    {
      "年度": 2017,
      "グループ": "K",
      "番号": 3,
      "支出先名": "西日本技術開発株式会社",
      "法人番号": "6290001017728",
      "業務概要": "地層変形シミュレータによる生産時の坑井健全性評価作業及び商業生産規模における広域地層変形解析作業",
      "支出額": 35.0
    },
    {
      "年度": 2017,
      "グループ": "K",
      "番号": 4,
      "支出先名": "応用地質株式会社",
      "法人番号": "2010001034531",
      "業務概要": "室内試験装置分解モニタリング計測・評価作業",
      "支出額": 14.0
    },
    {
      "年度": 2017,
      "グループ": "K",
      "番号": 5,
      "支出先名": "シュルンベルジェ株式会社",
      "法人番号": "3021001012649",
      "業務概要": "平成29年度地震探査データ解釈ソフトウェア保守",
      "支出額": 5.0
    },
    {
      "年度": 2017,
      "グループ": "K",
      "番号": 6,
      "支出先名": "アルファ・メカテック",
      "法人番号": null,
      "業務概要": "堆積物内断層性状実験用リングせん断試験装置改造",
      "支出額": 4.0
    },
    {
      "年度": 2017,
      "グループ": "K",
      "番号": 7,
      "支出先名": "シュルンベルジェ株式会社",
      "法人番号": "3021001012649",
      "業務概要": "平成29年度物理検層解析ソフトウェア保守",
      "支出額": 4.0
    },
    {
      "年度": 2017,
      "グループ": "K",
      "番号": 8,
      "支出先名": "エア・ウォーター北海道株式会社",
      "法人番号": "4430001022194",
      "業務概要": "メタンハイドレート資源開発生産手法開発に係わる高圧ガス設備の定期自主検査",
      "支出額": 3.0
    },
    {
      "年度": 2017,
      "グループ": "K",
      "番号": 9,
      "支出先名": "株式会社タナカ",
      "法人番号": "9430001010244",
      "業務概要": "メタンハイドレート分解速度解析装置改修　一式",
      "支出額": 3.0
    },
    {
      "年度": 2017,
      "グループ": "K",
      "番号": 10,
      "支出先名": "ブルカージャパン株式会社",
      "法人番号": "8020001059836",
      "業務概要": "天然ハイドレートコアガス密度精密解析装置保守",
      "支出額": 2.0
    }
  ],
  "アウトカム": [
    {
      "成果目標": "三次元物理探査により得られた地質データを処理及び解釈した結果として、油ガスが埋蔵している可能性のある地質構造を1調査海域あたり3つ以上見つける。",
      "成果指標": "油ガスが埋蔵している可能性のある地質構造の数／調査海域数",
      "単位": "構造",
      "目標値": null,
      "目標最終年度": null,
      "成果実績": [
        {
          "年度": 2015,
          "成果実績": null,
          "目標値": null
        },
        {
          "年度": 2016,
          "成果実績": null,
          "目標値": null
        },
        {
          "年度": 2017,
          "成果実績": 5.0,
          "目標値": 9.0
        }
      ]
    },
    {
      "成果目標": "基礎試錐により得られた詳細な地質データ等から、想定石油システム等の事前スタディとの整合性を検証した結果において、5段階中の3点以上を獲得すること。",
      "成果指標": "5:想定どおりに油ガス徴を示す地層が発見され、事前スタディとの極めて高い整合性を確認。\n4:油ガス徴を示す地層が発見され、事前スタディとの高い整合性を確認。\n3:油ガス徴を示す地層が発見され、事前スタディとの整合性を一部確認\n2:油ガス徴を示す地層は発見されないが、事前スタディとの整合性を一部確認\n1:油ガス徴を示す地層は発見されず、事前スタディとの整合性も確認されない。",
      "単位": "点",
      "目標値": null,
      "目標最終年度": null,
      "成果実績": [
        {
          "年度": 2015,
          "成果実績": null,
          "目標値": null
        },
        {
          "年度": 2016,
          "成果実績": null,
          "目標値": null
        },
        {
          "年度": 2017,
          "成果実績": null,
          "目標値": null
        }
      ]
    },
    {
      "成果目標": "本事業による補助を受け、掘削調査を行った海域において、事業終了後8年以内に1件以上の開発着手を目指す。",
      "成果指標": "本事業による補助を受け、事業終了後8年以内に開発着手した件数",
      "単位": "点",
      "目標値": null,
      "目標最終年度": null,
      "成果実績": [
        {
          "年度": 2015,
          "成果実績": null,
          "目標値": null
        },
        {
          "年度": 2016,
          "成果実績": null,
          "目標値": null
        },
        {
          "年度": 2017,
          "成果実績": null,
          "目標値": null
        }
      ]
    },
    {
      "成果目標": "メタンハイドレートについて、外部有識者によるの事業進捗状況の確認において、5段階中の3点以上を獲得すること。\n\nなお、商業的産出に向けた技術整備として、以下の目標を掲げている。\n　①数ヶ月以上のガス生産実験の実施\n　②商業化の判断が可能なガス生産量の確保。\n　③商業化の判断が可能な濃集帯の把握",
      "成果指標": "※事業の進捗について、外部有識者が評価（5段階）\n5:質・量の両面において極めて優れたパフォーマンスを実現\n4:質・量のどちらか一方において極めて優れたパフォーマンスを実現\n3:質・量の両面において着実に実施\n2:質・量のどちらか一方において未達、若しくは、研究の推進に当たって問題となる事象が発生\n1:質・量の両面において大幅な未達、若しくは、研究の推進に当たって重大な問題となる事象が発生",
      "単位": "点",
      "目標値": "3",
      "目標最終年度": 2018,
      "成果実績": [
        {
          "年度": 2015,
          "成果実績": null,
          "目標値": null
        },
        {
          "年度": 2016,
          "成果実績": null,
          "目標値": null
        },
        {
          "年度": 2017,
          "成果実績": null,
          "目標値": null
        }
      ]
    },
    {
      "成果目標": "メタンハイドレートについて、民間企業が主導する商業化のためのプロジェクトが平成30年代後半に開始される。",
      "成果指標": "※下記の5段階で評価\n5：商業化のためのプロジェクトが開始された。\n4：商業化のためのプロジェクトの概要に基づく準備が実施された。\n3：商業化のためのプロジェクトの概要が検討された。\n2：商業化のためのプロジェクトに必要な生産技術が確立させた。\n1：商業化のためのプロジェクトに必要な生産技術開発が実施された。",
      "単位": "点",
      "目標値": "5",
      "目標最終年度": 2027,
      "成果実績": [
        {
          "年度": 2015,
          "成果実績": null,
          "目標値": null
        },
        {
          "年度": 2016,
          "成果実績": null,
          "目標値": null
        },
        {
          "年度": 2017,
          "成果実績": null,
          "目標値": null
        }
      ]
    }
  ],
  "定量的な目標が設定できない理由": null,
  "アウトプット": [
    {
      "活動指標": "三次元物理探査を計画的に進めることにより、我が国周辺海域の石油・天然ガスの賦存状況を把握する。具体的には、平成30年度までに累計概ね6.2万km2の三次元物理探査を行う。",
      "単位": "万km2",
      "活動実績": [
        {
          "年度": 2015,
          "活動実績": null,
          "当初見込み": null
        },
        {
          "年度": 2016,
          "活動実績": null,
          "当初見込み": null
        },
        {
          "年度": 2017,
          "活動実績": 5.4,
          "当初見込み": null
        }
      ]
    },
    {
      "活動指標": "三次元物理探査の結果から石油・天然ガスの賦存が期待される地質構造について、3年に1本（＝1年あたり1/3本）の基礎試錐を行う。",
      "単位": "本",
      "活動実績": [
        {
          "年度": 2015,
          "活動実績": null,
          "当初見込み": null
        },
        {
          "年度": 2016,
          "活動実績": null,
          "当初見込み": null
        },
        {
          "年度": 2017,
          "活動実績": 0.3333333333333333,
          "当初見込み": 0.3333333333333333
        }
      ]
    },
    {
      "活動指標": "民間企業が自ら行う掘削調査を5年間で3本以上支援する。",
      "単位": "本",
      "活動実績": [
        {
          "年度": 2015,
          "活動実績": null,
          "当初見込み": null
        },
        {
          "年度": 2016,
          "活動実績": null,
          "当初見込み": null
        },
        {
          "年度": 2017,
          "活動実績": null,
          "当初見込み": null
        }
      ]
    },
    {
      "活動指標": "メタンハイドレートの研究開発に関する論文等発表数",
      "単位": "本",
      "活動実績": [
        {
          "年度": 2015,
          "活動実績": null,
          "当初見込み": null
        },
        {
          "年度": 2016,
          "活動実績": null,
          "当初見込み": null
        },
        {
          "年度": 2017,
          "活動実績": 96.0,
          "当初見込み": 65.0
        }
      ]
    }
  ],
  "url": "https://www.meti.go.jp/information_2/publicoffer/review2018/saisyu/29020800METI.xlsx",
  "関連する過去のレビューシート": [
    {
      "府省庁": "経済産業省",
      "事業番号1": "新29",
      "事業番号2": "0011",
      "事業番号3": null,
      "年度": 2010
    }
  ]
}