{
  "ID": null,
  "事業ID": null,
  "url": null,
  "公開年度": 2023,
  "事業名": "資源循環システム高度化促進事業",
  "開始年度": 2017,
  "終了年度": 2022,
  "府省庁": "経済産業省",
  "事業番号1": "2023",
  "事業番号2": "経産",
  "事業番号3": "22",
  "事業番号4": "0309",
  "事業番号5": null,
  "事業番号": "2023-経産-22-0309",
  "担当部局庁": "産業技術環境局",
  "担当課室": "資源循環経済課",
  "作成責任者": "課長　田中　将吾",
  "会計区分": [
    "エネルギー対策特別会計エネルギー需給勘定"
  ],
  "事業目的": "国内外の地上資源の高度活用システムを構築し、国際的に需要の増大が見込まれる有用金属の安定確保及び省資源・省エネルギー化を実現するための技術開発を行う。具体的には、安価で高品質なリサイクル材の安定的な生産・供給を実現するため、廃小型家電等を製品レベル・部品レベルで自動選別するプロセス及び高効率な製錬プロセスなどを構築するための研究開発を行うことで、世界に先駆けた高効率かつ省エネルギー効果の高い資源循環システムの構築を目指す。",
  "事業概要": "我が国の都市鉱山を有効に活用するため、スクラップの選別システムや製錬システム等の革新につながる研究開発や、これらをシステム化する情報技術等を有効活用することによって、動静脈産業が一体となった戦略的な資源循環システムの構築を行う。",
  "実施方法": [
    "交付"
  ],
  "予算": [
    {
      "年度": 2020,
      "当初予算": 735.0,
      "補正予算": 0.0,
      "前年度から繰越し": 574.0,
      "翌年度へ繰越し": -405.0,
      "予備費等": 72.0,
      "予算計": 976.0,
      "執行額": 973.0
    },
    {
      "年度": 2021,
      "当初予算": 570.0,
      "補正予算": 0.0,
      "前年度から繰越し": 405.0,
      "翌年度へ繰越し": -203.0,
      "予備費等": -173.0,
      "予算計": 599.0,
      "執行額": 599.0
    },
    {
      "年度": 2022,
      "当初予算": 315.0,
      "補正予算": 0.0,
      "前年度から繰越し": 203.0,
      "翌年度へ繰越し": 0.0,
      "予備費等": 0.0,
      "予算計": 518.0,
      "執行額": 481.0
    },
    {
      "年度": 2023,
      "当初予算": 0.0,
      "補正予算": 0.0,
      "前年度から繰越し": 0.0,
      "翌年度へ繰越し": 0.0,
      "予備費等": 0.0,
      "予算計": 0.0
    },
    {
      "年度": 2024,
      "要求額": 0.0
    }
  ],
  "支出先": [
    {
      "年度": 2022,
      "グループ": "A",
      "番号": 1,
      "支出先名": "国立研究開発法人新エネルギー・産業技術総合開発機構",
      "法人番号": "2020005008480",
      "業務概要": "プロジェクト管理等",
      "支出額": 481.0
    },
    {
      "年度": 2022,
      "グループ": "B",
      "番号": 1,
      "支出先名": "国立研究開発法人産業技術総合研究所",
      "法人番号": "7010005005425",
      "業務概要": "高効率な資源循環システムを構築するためのリサイクル技術の研究開発事業",
      "支出額": 177.3
    },
    {
      "年度": 2022,
      "グループ": "B",
      "番号": 2,
      "支出先名": "株式会社三徳",
      "法人番号": "3140001001609",
      "業務概要": "コスト計算・実用化の課題明確化",
      "支出額": 80.9
    },
    {
      "年度": 2022,
      "グループ": "B",
      "番号": 3,
      "支出先名": "佐藤鉄工株式会社",
      "法人番号": "3230001006466",
      "業務概要": "破砕機開発・統合システム製造",
      "支出額": 48.4
    },
    {
      "年度": 2022,
      "グループ": "B",
      "番号": 4,
      "支出先名": "大栄環境株式会社",
      "法人番号": "6120101041611",
      "業務概要": "統合システム試験導入・小家電データベース・性能評価",
      "支出額": 42.4
    },
    {
      "年度": 2022,
      "グループ": "B",
      "番号": 5,
      "支出先名": "国立大学法人京都大学",
      "法人番号": "3130005005532",
      "業務概要": "溶解塩を利用した濃縮系少量材料のリサイクル技術開発（フッ化物系）",
      "支出額": 22.4
    },
    {
      "年度": 2022,
      "グループ": "B",
      "番号": 6,
      "支出先名": "国立大学法人佐賀大学",
      "法人番号": "1300005002712",
      "業務概要": "高精密金属イオンサイズ認識分離技術開発（溶媒抽出系開発）",
      "支出額": 16.9
    },
    {
      "年度": 2022,
      "グループ": "B",
      "番号": 7,
      "支出先名": "国立大学法人大阪大学",
      "法人番号": "4120905002554",
      "業務概要": "溶解塩を利用した濃縮系少量材料のリサイクル技術開発（高温塩化物系）",
      "支出額": 15.1
    },
    {
      "年度": 2022,
      "グループ": "B",
      "番号": 8,
      "支出先名": "国立研究開発法人日本原子力研究開発機構",
      "法人番号": "6050005002007",
      "業務概要": "配位子開発・分離機構解析",
      "支出額": 15.0
    },
    {
      "年度": 2022,
      "グループ": "B",
      "番号": 9,
      "支出先名": "株式会社リーテム",
      "法人番号": "9010001032090",
      "業務概要": "選別装置の試験導入",
      "支出額": 2.2
    },
    {
      "年度": 2022,
      "グループ": "B",
      "番号": 10,
      "支出先名": "ＤＯＷＡエコシステム株式会社",
      "法人番号": "5010001099183",
      "業務概要": "製錬原料基準設定",
      "支出額": 0.2
    },
    {
      "年度": 2022,
      "グループ": "C",
      "番号": 1,
      "支出先名": "国立大学法人神戸大学",
      "法人番号": "5140005004060",
      "業務概要": "高精密金属イオンサイズ認識分離技術開発（精密有機合成）",
      "支出額": 7.4
    },
    {
      "年度": 2022,
      "グループ": "C",
      "番号": 2,
      "支出先名": "国立大学法人北海道大学",
      "法人番号": "6430005004014",
      "業務概要": "廃部品自動選別技術開発（細粒選別装置検討）",
      "支出額": 5.0
    },
    {
      "年度": 2022,
      "グループ": "C",
      "番号": 3,
      "支出先名": "国立大学法人東京大学",
      "法人番号": "5010005007398",
      "業務概要": "廃部品自動選別技術開発（将来需要予測等）",
      "支出額": 2.5
    },
    {
      "年度": 2022,
      "グループ": "C",
      "番号": 4,
      "支出先名": "国立大学法人秋田大学",
      "法人番号": "2410005001280",
      "業務概要": "動静脈連携システムの開発",
      "支出額": 2.5
    },
    {
      "年度": 2022,
      "グループ": "D",
      "番号": 1,
      "支出先名": "株式会社アビヅ",
      "法人番号": "9180001053731",
      "業務概要": "タイにおけるWEEEリサイクルプラントの実証試験",
      "支出額": 45.0
    }
  ],
  "関連する過去のレビューシート": [],
  "アウトカム": [],
  "アウトプット": [],
  "主要施策": null
}