{
  "ID": 18647,
  "事業ID": 8158,
  "公開年度": 2018,
  "事業名": "国産農産物消費拡大事業のうち日本の食消費拡大国民運動推進事業",
  "開始年度": 2016,
  "終了年度": 2018,
  "府省庁": "農林水産省",
  "事業番号1": null,
  "事業番号2": "0011",
  "事業番号3": null,
  "担当部局庁": "食料産業局",
  "担当課室": "食文化・市場開拓課",
  "作成責任者": "食文化・市場開拓課長\n西　経子",
  "会計区分": [
    "一般会計"
  ],
  "事業目的": "食料の安定的な供給に向け、農林水産業の持続的発展と国産食材を主たる原料として使用する食品産業の健全な発展を図るためには、国産農林水産物の消費拡大を推進することが重要であるが、国産農林水産物の消費拡大に対する意識醸成が課題である。このため、国産農林水産物の消費拡大の推進に向けて、食や農林漁業に対する理解・関心の向上を図るとともに、民間事業者・団体、消費者、国が一体となって国産農林水産物の消費拡大に向けた取組を実施する国民運動を展開。",
  "事業概要": "国産農林水産物の消費拡大を推進するため、以下の取組を実施。\n①食の魅力発掘による消費拡大のための国民運動推進事業 【委託費】\n国産農林水産物の需要創出、販路開拓等の取組を支援するとともに、国産農林水産物の消費拡大を推進するフード・アクション・ニッポン事務局が地域別・品目別の取組をとりまとめて一元的な広報活動、食の魅力普及活動、顕彰活動を行い、それらの効果測定を実施。\n②地域の食の絆強化推進運動事業 【補助率：定額】\n学校給食等と連携した地産地消の取組を推進するためのコーディネーターの育成等を支援。",
  "実施方法": [
    "委託・請負",
    "補助"
  ],
  "主要施策": [
    "その他"
  ],
  "予算": [
    {
      "年度": 2015,
      "当初予算": 0.0,
      "補正予算": 0.0,
      "前年度から繰越し": 0.0,
      "翌年度へ繰越し": 0.0,
      "予備費等": 0.0,
      "予算計": 0.0,
      "執行額": 0.0
    },
    {
      "年度": 2016,
      "当初予算": 388.0,
      "補正予算": 0.0,
      "前年度から繰越し": 0.0,
      "翌年度へ繰越し": 0.0,
      "予備費等": 0.0,
      "予算計": 388.0,
      "執行額": 356.0
    },
    {
      "年度": 2017,
      "当初予算": 288.0,
      "補正予算": 0.0,
      "前年度から繰越し": 0.0,
      "翌年度へ繰越し": 0.0,
      "予備費等": 0.0,
      "予算計": 288.0,
      "執行額": 280.0
    },
    {
      "年度": 2018,
      "当初予算": 232.0,
      "補正予算": 0.0,
      "前年度から繰越し": 0.0,
      "翌年度へ繰越し": 0.0,
      "予備費等": 0.0,
      "予算計": 232.0
    },
    {
      "年度": 2019,
      "要求額": 204.0
    }
  ],
  "支出先": [
    {
      "年度": 2017,
      "グループ": "A",
      "番号": 1,
      "支出先名": "株式会社ＪＴＢコーポレートセールス",
      "法人番号": "7011101055132",
      "業務概要": "国産農林水産物の消費拡大に向けた優良産品表彰業務",
      "支出額": 117.0
    },
    {
      "年度": 2017,
      "グループ": "A",
      "番号": 2,
      "支出先名": "株式会社電通ライブ",
      "法人番号": "4010001050790",
      "業務概要": "食と農林漁業の祭典イベント運営業務",
      "支出額": 101.0
    },
    {
      "年度": 2017,
      "グループ": "A",
      "番号": 3,
      "支出先名": "一般社団法人日本協同組合連携機構",
      "法人番号": "1011105004792",
      "業務概要": "日本の食消費拡大国民運動推進業務",
      "支出額": 27.0
    },
    {
      "年度": 2017,
      "グループ": "A",
      "番号": 4,
      "支出先名": "株式会社野村総合研究所",
      "法人番号": "4010001054032",
      "業務概要": "国産農林水産物の消費拡大施策に係る調査・分析業務",
      "支出額": 25.0
    },
    {
      "年度": 2017,
      "グループ": "B",
      "番号": 1,
      "支出先名": "一般財団法人都市農山漁村交流活性化機構",
      "法人番号": "2010005003887",
      "業務概要": "学校給食等と連携した地産地消の取組に向けたコーディネイター育成等事業",
      "支出額": 11.0
    },
    {
      "年度": 2017,
      "グループ": "C",
      "番号": 1,
      "支出先名": "ドリームエッジ株式会社",
      "法人番号": "4013201014169",
      "業務概要": "web運営等",
      "支出額": 43.0
    },
    {
      "年度": 2017,
      "グループ": "C",
      "番号": 2,
      "支出先名": "株式会社電通",
      "法人番号": "4010401048922",
      "業務概要": "ＰＲ業務等",
      "支出額": 32.0
    },
    {
      "年度": 2017,
      "グループ": "C",
      "番号": 3,
      "支出先名": "株式会社電通",
      "法人番号": "4010401048922",
      "業務概要": "企画制作等",
      "支出額": 3.0
    },
    {
      "年度": 2017,
      "グループ": "C",
      "番号": 4,
      "支出先名": "一般社団法人全国食の甲子園協会",
      "法人番号": "6011005005424",
      "業務概要": "イベント運営業務等",
      "支出額": 17.0
    },
    {
      "年度": 2017,
      "グループ": "C",
      "番号": 5,
      "支出先名": "一般社団法人ＣＳＶ開発機構",
      "法人番号": "7010405012698",
      "業務概要": "イベント運営業務等",
      "支出額": 12.0
    },
    {
      "年度": 2017,
      "グループ": "C",
      "番号": 6,
      "支出先名": "株式会社ワイワイルア",
      "法人番号": "7010401052351",
      "業務概要": "イベント運営業務等",
      "支出額": 4.0
    },
    {
      "年度": 2017,
      "グループ": "C",
      "番号": 7,
      "支出先名": "株式会社マーシュ",
      "法人番号": "2010901015886",
      "業務概要": "調査業務等",
      "支出額": 4.0
    },
    {
      "年度": 2017,
      "グループ": "C",
      "番号": 8,
      "支出先名": "株式会社電通パブリックリレーションズ",
      "法人番号": "2010001050202",
      "業務概要": "ＰＲ業務等",
      "支出額": 3.0
    },
    {
      "年度": 2017,
      "グループ": "C",
      "番号": 9,
      "支出先名": "リッキービジネスソリューション株式会社",
      "法人番号": "8011101033541",
      "業務概要": "セミナー運営業務等",
      "支出額": 3.0
    },
    {
      "年度": 2017,
      "グループ": "C",
      "番号": 10,
      "支出先名": "株式会社キースタッフ",
      "法人番号": "8040001048465",
      "業務概要": "セミナー運営業務等",
      "支出額": 2.0
    },
    {
      "年度": 2017,
      "グループ": "C",
      "番号": 11,
      "支出先名": "株式会社　ＮＯＰＰＯ",
      "法人番号": "9010001101944",
      "業務概要": "企画・実施運営活動費",
      "支出額": 2.0
    }
  ],
  "アウトカム": [
    {
      "成果目標": "国民運動に参加する事業者・団体等数を平成30年度までに12,000社にする",
      "成果指標": "国民運動に参加する事業者・団体数",
      "単位": "社",
      "目標値": "12000",
      "目標最終年度": 2018,
      "成果実績": [
        {
          "年度": 2015,
          "成果実績": null,
          "目標値": null
        },
        {
          "年度": 2016,
          "成果実績": 9553.0,
          "目標値": 10300.0
        },
        {
          "年度": 2017,
          "成果実績": 10192.0,
          "目標値": 11100.0
        }
      ]
    },
    {
      "成果目標": "学校給食における地場産物を使用する割合を平成32年度までに30%にする",
      "成果指標": "学校給食における地場産物を使用する割合　　　　　　　　　　　　　　　　　　　　　　　　　　　※「学校給食における地場産物を使用する割合」＝「地場産の品数」/「総食品数」",
      "単位": "％",
      "目標値": "30",
      "目標最終年度": 2020,
      "成果実績": [
        {
          "年度": 2015,
          "成果実績": null,
          "目標値": null
        },
        {
          "年度": 2016,
          "成果実績": 25.8,
          "目標値": 27.5
        },
        {
          "年度": 2017,
          "成果実績": 26.4,
          "目標値": 28.1
        }
      ]
    },
    {
      "成果目標": "国民運動を通じて「国産農林水産物を意識して購入するようになった」と回答する消費者の割合を平成30年度までに12％に向上する",
      "成果指標": "国民運動を通じて「国産農林水産物を意識して購入するようになった」と回答する消費者の割合　　　　　　　　　　　　　　　　　　　　　　　　　　　　　　　   ※「フード・アクション・ニッポン（以下、FANという）の取組によって国産農林水産物を意識して購入するようになった割合」＝「FANの取組を経験し、国産品を意識して購入するようになった人数÷調査人数」Ｘ「FANの取組の経験人数÷調査人数」",
      "単位": "％",
      "目標値": "12",
      "目標最終年度": 2018,
      "成果実績": [
        {
          "年度": 2015,
          "成果実績": null,
          "目標値": null
        },
        {
          "年度": 2016,
          "成果実績": 7.482000000000001,
          "目標値": 6.6
        },
        {
          "年度": 2017,
          "成果実績": 6.6785,
          "目標値": 9.3
        }
      ]
    }
  ],
  "定量的な目標が設定できない理由": null,
  "アウトプット": [
    {
      "活動指標": "①国産農林水産物消費拡大運動に参加した消費者の人数",
      "単位": "千人",
      "活動実績": [
        {
          "年度": 2015,
          "活動実績": null,
          "当初見込み": null
        },
        {
          "年度": 2016,
          "活動実績": 1566.0,
          "当初見込み": 1280.0
        },
        {
          "年度": 2017,
          "活動実績": 2484.0,
          "当初見込み": 1200.0
        }
      ]
    },
    {
      "活動指標": "②コーディネーター育成研修会及びコーディネーター派遣の参加者数",
      "単位": "人",
      "活動実績": [
        {
          "年度": 2015,
          "活動実績": null,
          "当初見込み": null
        },
        {
          "年度": 2016,
          "活動実績": 376.0,
          "当初見込み": 340.0
        },
        {
          "年度": 2017,
          "活動実績": 568.0,
          "当初見込み": 340.0
        }
      ]
    }
  ],
  "url": "http://www.maff.go.jp/j/budget/review/h30/saisyu/ http:/www.maff.go.jp/j/budget/review/h30/saisyu/xls/haba/290011_nousui_s.xlsx",
  "関連する過去のレビューシート": [
    {
      "府省庁": "農林水産省",
      "事業番号1": null,
      "事業番号2": "0011",
      "事業番号3": null,
      "年度": 2015
    }
  ]
}