{
  "ID": null,
  "事業ID": null,
  "url": null,
  "公開年度": 2023,
  "事業名": "OECMを活用した健全な生態系の回復及び連結促進事業",
  "開始年度": 2003,
  "終了年度": null,
  "府省庁": "環境省",
  "事業番号1": "2023",
  "事業番号2": "環境",
  "事業番号3": "22",
  "事業番号4": "0150",
  "事業番号5": null,
  "事業番号": "2023-環境-22-0150",
  "担当部局庁": "自然環境局",
  "担当課室": "自然環境計画課\n生物多様性主流化室\n野生生物課",
  "作成責任者": "自然環境計画課長　則久　雅司\n生物多様性主流化室長　浜島　直子\n野生生物課長　中澤　圭一",
  "会計区分": [
    "一般会計"
  ],
  "事業目的": "生物多様性の把握及び多様な主体の連携・協働による保全・回復の取組を促進し、30by30目標達成を通じた健全な生態系の確保を図る。",
  "事業概要": "生物多様性の重要度や保全活動の効果を「見える化」できる仕組みの構築や、重要地域に生息・生育する種等の詳細情報の収集・整理、「自然共生サイト」認定を通じたOECM（保護地域以外で生物多様性保全に資する地域）の設定・管理等を進めることで、生態系ネットワークを構築し、健全な生態系の確保を図る。\nそのために、地方公共団体や市民団体で構成される協議会等が実施する生物多様性保全の取組を支援する。\nまた、NPOや地域住民、関係行政機関など多様な主体が連携して実施する自然再生活動を全国的に推進する。",
  "実施方法": [
    "委託・請負",
    "交付"
  ],
  "予算": [
    {
      "年度": 2020,
      "当初予算": 193.0,
      "補正予算": 0.0,
      "前年度から繰越し": 14.0,
      "翌年度へ繰越し": -7.0,
      "予備費等": 0.0,
      "予算計": 200.0,
      "執行額": 185.0
    },
    {
      "年度": 2021,
      "当初予算": 227.0,
      "補正予算": 0.0,
      "前年度から繰越し": 7.0,
      "翌年度へ繰越し": -7.0,
      "予備費等": 0.0,
      "予算計": 227.0,
      "執行額": 214.0
    },
    {
      "年度": 2022,
      "当初予算": 353.0,
      "補正予算": 0.0,
      "前年度から繰越し": 7.0,
      "翌年度へ繰越し": -10.0,
      "予備費等": 0.0,
      "予算計": 350.0,
      "執行額": 315.0
    },
    {
      "年度": 2023,
      "当初予算": 266.0,
      "補正予算": 0.0,
      "前年度から繰越し": 10.0,
      "翌年度へ繰越し": 0.0,
      "予備費等": 0.0,
      "予算計": 276.0
    },
    {
      "年度": 2024,
      "要求額": 419.0
    }
  ],
  "支出先": [
    {
      "年度": 2022,
      "グループ": "A",
      "番号": 1,
      "支出先名": "琵琶湖外来水生植物対策協議会",
      "法人番号": null,
      "業務概要": "琵琶湖地域沿岸植生回復・復元事業",
      "支出額": 12.5
    },
    {
      "年度": 2022,
      "グループ": "A",
      "番号": 2,
      "支出先名": "浜松市",
      "法人番号": "3000020221309",
      "業務概要": "浜松市クリハラリス分布拡大防止及び低密度化事業",
      "支出額": 8.0
    },
    {
      "年度": 2022,
      "グループ": "A",
      "番号": 3,
      "支出先名": "千葉県",
      "法人番号": "4000020120006",
      "業務概要": "手賀沼・印旛沼流域ナガエツルノゲイトウ等外来水生植物対策事業",
      "支出額": 8.0
    },
    {
      "年度": 2022,
      "グループ": "A",
      "番号": 4,
      "支出先名": "きさらづ里山里海未来拠点形成推進協議会",
      "法人番号": null,
      "業務概要": "きさらづ里山里海プロジェクト",
      "支出額": 7.0
    },
    {
      "年度": 2022,
      "グループ": "A",
      "番号": 5,
      "支出先名": "徳島アルゼンチンアリ対策協議会",
      "法人番号": null,
      "業務概要": "徳島アルゼンチンアリ広域対策事業",
      "支出額": 5.0
    },
    {
      "年度": 2022,
      "グループ": "A",
      "番号": 6,
      "支出先名": "鳥ノ巣半島生物多様性保全推進協議会",
      "法人番号": null,
      "業務概要": "鳥ノ巣半島生物多様性保全推進事業",
      "支出額": 4.0
    },
    {
      "年度": 2022,
      "グループ": "A",
      "番号": 7,
      "支出先名": "熊本県特定外来生物スパルティナ属対策協議会",
      "法人番号": null,
      "業務概要": "熊本県特定外来生物スパルティナ属対策事業",
      "支出額": 4.0
    },
    {
      "年度": 2022,
      "グループ": "A",
      "番号": 8,
      "支出先名": "対馬市生物多様性協議会",
      "法人番号": null,
      "業務概要": "対馬地域ツマアカスズメバチ巣探索技術開発事業",
      "支出額": 3.0
    },
    {
      "年度": 2022,
      "グループ": "A",
      "番号": 9,
      "支出先名": "三方五湖生物多様性保全協議会",
      "法人番号": null,
      "業務概要": "三方五湖の持続可能な地域づくり事業",
      "支出額": 3.0
    },
    {
      "年度": 2022,
      "グループ": "A",
      "番号": 10,
      "支出先名": "出水ツル越冬地生物多様性協議会",
      "法人番号": null,
      "業務概要": "出水ツル越冬地の持続可能な自然環境の保全と地域との共生に向けた取組",
      "支出額": 3.0
    },
    {
      "年度": 2022,
      "グループ": "B",
      "番号": 1,
      "支出先名": "滋賀県",
      "法人番号": "7000020250007",
      "業務概要": "生物多様性保全回復施設整備事業（外来水生植物対策等）",
      "支出額": 15.0
    },
    {
      "年度": 2022,
      "グループ": "B",
      "番号": 2,
      "支出先名": "京都府",
      "法人番号": "2000020260002",
      "業務概要": "亀岡市保津地域アユモドキ生息地域保全回復整備事業",
      "支出額": 5.0
    },
    {
      "年度": 2022,
      "グループ": "B",
      "番号": 3,
      "支出先名": "群馬県",
      "法人番号": "7000020100005",
      "業務概要": "赤城山覚満淵植生保護事業",
      "支出額": 0.1
    },
    {
      "年度": 2022,
      "グループ": "C",
      "番号": 1,
      "支出先名": "アビームコンサルティング株式会社",
      "法人番号": "8010001085296",
      "業務概要": "OECM情報システム（仮称）構築に向けた要件定義書作成等業務",
      "支出額": 45.0
    },
    {
      "年度": 2022,
      "グループ": "C",
      "番号": 2,
      "支出先名": "いであ株式会社",
      "法人番号": "7010901005494",
      "業務概要": "自然共生エリア（仮称）認定加速化等業務",
      "支出額": 40.0
    },
    {
      "年度": 2022,
      "グループ": "C",
      "番号": 3,
      "支出先名": "株式会社エイト日本技術開発",
      "法人番号": "7260001000735",
      "業務概要": "生態系回復手法検討等及び生態系回復を要する劣化地パターン分類調査業務",
      "支出額": 14.0
    },
    {
      "年度": 2022,
      "グループ": "C",
      "番号": 4,
      "支出先名": "いであ株式会社",
      "法人番号": "7010901005494",
      "業務概要": "自然共生サイト（仮称）認定に係る経済的インセンティブ等調査検討業務",
      "支出額": 9.0
    },
    {
      "年度": 2022,
      "グループ": "C",
      "番号": 5,
      "支出先名": "株式会社地域環境計画",
      "法人番号": "6010901007401",
      "業務概要": "自然共生サイト（仮称）伴走支援手法検討業務",
      "支出額": 4.0
    },
    {
      "年度": 2022,
      "グループ": "C",
      "番号": 6,
      "支出先名": "一般財団法人自然環境研究センター",
      "法人番号": "6010505001148",
      "業務概要": "G7日本開催に向けた生物多様性保全の国際的な動向等調査業務",
      "支出額": 1.0
    },
    {
      "年度": 2022,
      "グループ": "C",
      "番号": 7,
      "支出先名": "一般社団法人自然環境文化推進機構",
      "法人番号": "6130005014266",
      "業務概要": "社寺林等におけるOECM検討調査業務",
      "支出額": 1.0
    },
    {
      "年度": 2022,
      "グループ": "C",
      "番号": 8,
      "支出先名": "株式会社地域環境計画",
      "法人番号": "6010901007401",
      "業務概要": "沿岸域における自然共生サイト認定に向けた情報整理業務",
      "支出額": 0.4
    },
    {
      "年度": 2022,
      "グループ": "C",
      "番号": 9,
      "支出先名": "個人事業主",
      "法人番号": null,
      "業務概要": "自然共生サイト等ロゴマーク制作業務",
      "支出額": 0.3
    },
    {
      "年度": 2022,
      "グループ": "C",
      "番号": 10,
      "支出先名": "ヤマノ印刷株式会社",
      "法人番号": "2010001031248",
      "業務概要": "「生物多様性のための30by30アライアンス」の普及啓発ツール印刷業務",
      "支出額": 0.1
    },
    {
      "年度": 2022,
      "グループ": "D",
      "番号": 1,
      "支出先名": "株式会社一成",
      "法人番号": "8140001042490",
      "業務概要": "自然再生専門家会議開催支援等業務",
      "支出額": 7.7
    },
    {
      "年度": 2022,
      "グループ": "E",
      "番号": 1,
      "支出先名": "株式会社メッツ研究所",
      "法人番号": "8011201005449",
      "業務概要": "絶滅危惧種情報の収集・整理業務",
      "支出額": 8.5
    },
    {
      "年度": 2022,
      "グループ": "F",
      "番号": 1,
      "支出先名": "いであ株式会社",
      "法人番号": "7010901005494",
      "業務概要": "環境ＤＮＡ分析技術を用いた淡水魚類調査手法の標準化・一般化検討業務",
      "支出額": 9.9
    },
    {
      "年度": 2022,
      "グループ": "F",
      "番号": 2,
      "支出先名": "一般財団法人自然環境研究センター",
      "法人番号": "6010505001148",
      "業務概要": "環境ＤＮＡ分析技術を用いた両生類調査手法の標準化・一般化検討業務",
      "支出額": 3.9
    },
    {
      "年度": 2022,
      "グループ": "F",
      "番号": 3,
      "支出先名": "いであ株式会社",
      "法人番号": "7010901005494",
      "業務概要": "自然環境に生息する淡水魚類に関する環境ＤＮＡリファレンス情報整備業務",
      "支出額": 0.7
    },
    {
      "年度": 2022,
      "グループ": "G",
      "番号": 1,
      "支出先名": "株式会社環境総合リサーチ",
      "法人番号": "7130001033211",
      "業務概要": "環境ＤＮＡ分析技術を用いた両生類調査手法の標準化・一般化検討業務",
      "支出額": 1.7
    },
    {
      "年度": 2022,
      "グループ": "G",
      "番号": 2,
      "支出先名": "有限会社エコシス",
      "法人番号": "7100002010146",
      "業務概要": "環境ＤＮＡ分析技術を用いた淡水魚類調査手法の標準化・一般化検討業務",
      "支出額": 0.5
    }
  ],
  "関連する過去のレビューシート": []
}