{
  "ID": 569,
  "事業ID": 2461,
  "公開年度": 2015,
  "事業名": "放射性物質汚染廃棄物処理事業",
  "開始年度": 2012,
  "終了年度": null,
  "府省庁": "復興庁",
  "事業番号1": null,
  "事業番号2": "0219",
  "事業番号3": null,
  "担当部局庁": "復興庁",
  "担当課室": "統括官付参事官（予算・会計担当）",
  "作成責任者": "参事官　小瀬　達之",
  "会計区分": [
    "東日本大震災復興特別会計"
  ],
  "事業目的": "「平成二十三年三月十一日に発生した東北地方太平洋沖地震に伴う原子力発電所の事故（以下「事故」という。）により放出された放射性物質による環境の汚染への対処に関する特別措置法」（以下「放射性物質汚染対処特措法」という。）に基づき、汚染廃棄物対策地域内にある災害廃棄物等（以下、「対策地域内廃棄物」という。）及び事故由来放射性物質による汚染状態が基準を超える廃棄物（以下、「指定廃棄物」という。）を迅速に処理し、環境の汚染による人の健康又は生活環境への影響を速やかに低減すること等を目的とする。",
  "事業概要": "＜①対策地域内廃棄物処理＞\n  国は、対策地域内廃棄物について、対策地域内廃棄物処理計画（平成25年12月一部改定）に基づき、処理を行う。具体的には、帰還の妨げとなる廃棄物の撤去と仮置場への搬入を優先目標として、可能な限り再生利用を図りつつ、仮置場への搬入や仮設焼却施設における焼却処理等を進めていく。\n\n＜②指定廃棄物処理＞\n　福島県内の指定廃棄物については、富岡町の民間管理型最終処分場への搬入計画を具体化するため地元との調整を進めている。最終処分場が確保されるまでの間、指定廃棄物の保管の負担を軽減するため、焼却、乾燥などの中間処理の事業を実施する。\n  他県については、既存の廃棄物処理施設の活用について引き続き検討を行いつつ、指定廃棄物が大量に発生し、保管状況がひっ迫している５県（宮城県、茨城県、栃木県、群馬県、千葉県）については、県や地元との意見交換等を重視して、丁寧に手順を踏みつつ、必要な長期管理施設の確保に向けた取組を着実に進めて行く。\n\n＜③廃棄物処理施設等モニタリング＞\n　地方公共団体等が管理する特定一般廃棄物処理施設、特定産業廃棄物処理施設に対して、放射性物質汚染対処特措法で義務付けられているモニタリングに係る経費を補助する（補助率：定額）。\n\n＜④農林業系汚染廃棄物の処理加速化事業＞\n　従来、飼料・肥料等として利用されていた稲わら、牧草、きのこ原木等の農林業系副産物が事故により放出された放射性物質に汚染され、廃棄物として大量に発生しているが、その処理は進まず、農家の敷地内等に滞留し、その生活環境等に大きな影響を及ぼしているため、農林業系廃棄物を処理する市町村等に対し、事業実施に必要な経費の一部を国が補助することにより、その処理を加速化する（補助率：１／２）。",
  "実施方法": [
    "委託・請負",
    "補助"
  ],
  "主要施策": [
    "その他"
  ],
  "予算": [
    {
      "年度": 2012,
      "当初予算": 77224.0,
      "補正予算": 10427.0,
      "前年度から繰越し": 0.0,
      "翌年度へ繰越し": 0.0,
      "予備費等": 0.0,
      "予算計": 13071.0,
      "執行額": 6823.0
    },
    {
      "年度": 2013,
      "当初予算": 97100.0,
      "補正予算": 0.0,
      "前年度から繰越し": 74580.0,
      "翌年度へ繰越し": 0.0,
      "予備費等": 0.0,
      "予算計": 91367.0,
      "執行額": 23610.0
    },
    {
      "年度": 2014,
      "当初予算": 138012.0,
      "補正予算": 0.0,
      "前年度から繰越し": 80313.0,
      "翌年度へ繰越し": 0.0,
      "予備費等": 0.0,
      "予算計": 145913.0,
      "執行額": 40071.0
    },
    {
      "年度": 2015,
      "当初予算": 138681.0,
      "補正予算": 0.0,
      "前年度から繰越し": 72412.0,
      "翌年度へ繰越し": 0.0,
      "予備費等": 0.0,
      "予算計": 211093.0
    },
    {
      "年度": 2016,
      "要求額": 221488.0
    }
  ],
  "支出先": [
    {
      "年度": 2014,
      "グループ": "A",
      "番号": 1,
      "支出先名": "メディアインターナショナル(株)",
      "法人番号": null,
      "業務概要": "平成26年度フレキシブルコンテナの購入（単価契約）",
      "支出額": 666.0
    },
    {
      "年度": 2014,
      "グループ": "A",
      "番号": 2,
      "支出先名": "横山建設(株)",
      "法人番号": null,
      "業務概要": "平成26年度対策地域内４市町における被災船舶解体撤去工事",
      "支出額": 206.0
    },
    {
      "年度": 2014,
      "グループ": "A",
      "番号": 3,
      "支出先名": "応用地質(株)",
      "法人番号": null,
      "業務概要": "平成26年度汚染廃棄物対策地域における廃棄物処理に係る調査・設計業務",
      "支出額": 199.0
    },
    {
      "年度": 2014,
      "グループ": "A",
      "番号": 4,
      "支出先名": "一般財団法人日本環境衛生センタ－",
      "法人番号": null,
      "業務概要": "平成26年度福島県内の汚染廃棄物等の減容化処理等に係る技術支援業務（汚染廃棄物対策地域分）",
      "支出額": 190.0
    },
    {
      "年度": 2014,
      "グループ": "A",
      "番号": 5,
      "支出先名": "（株）野村総合研究所",
      "法人番号": null,
      "業務概要": "平成26年度福島環境再生事務所における組織体制構築及び業務の円滑かつ継続的な推進支援業務",
      "支出額": 132.0
    },
    {
      "年度": 2014,
      "グループ": "A",
      "番号": 6,
      "支出先名": "双葉地方広域市町村圏組合",
      "法人番号": null,
      "業務概要": "平成26年度福島県双葉郡内市町村の警戒区域見直しに伴う廃棄物焼却等業務",
      "支出額": 99.0
    },
    {
      "年度": 2014,
      "グループ": "A",
      "番号": 7,
      "支出先名": "(株)電通",
      "法人番号": null,
      "業務概要": "平成26年度放射性物質汚染廃棄物等の処理に関する啓発普及等支援業務（汚染廃棄物対策地域分）",
      "支出額": 83.0
    },
    {
      "年度": 2014,
      "グループ": "A",
      "番号": 8,
      "支出先名": "（株）釜屋",
      "法人番号": null,
      "業務概要": "平成26年度（平成25年度繰越）対策地域内廃棄物（廃家電）中間処理等業務",
      "支出額": 48.0
    },
    {
      "年度": 2014,
      "グループ": "A",
      "番号": 9,
      "支出先名": "エヌエス環境(株)",
      "法人番号": null,
      "業務概要": "平成26年度汚染廃棄物対策地域における廃棄物仮置場管理等調査業務",
      "支出額": 41.0
    },
    {
      "年度": 2014,
      "グループ": "A",
      "番号": 10,
      "支出先名": "（株）高島テクノロジーセンター",
      "法人番号": null,
      "業務概要": "平成26年度（平成25年度繰越）対策地域内4市町村における被災建物等調査業務",
      "支出額": 36.0
    },
    {
      "年度": 2014,
      "グループ": "B",
      "番号": 1,
      "支出先名": "日本国土開発（株）",
      "法人番号": null,
      "業務概要": "平成26年度東日本大震災により生じた対策地域内廃棄物の国直轄処理業務（南相馬市小沢・村上・浦尻）における災害廃棄物収集・運搬・選別等業務",
      "支出額": 8262.0
    },
    {
      "年度": 2014,
      "グループ": "B",
      "番号": 2,
      "支出先名": "(株)中里工務店",
      "法人番号": null,
      "業務概要": "平成26年度（平成25年度繰越）南相馬市警戒区域見直しに伴う建物等解体撤去工事",
      "支出額": 535.0
    },
    {
      "年度": 2014,
      "グループ": "B",
      "番号": 3,
      "支出先名": "（株）中里工務店",
      "法人番号": null,
      "業務概要": "平成26年度（平成25年度繰越）南相馬市警戒区域見直しに伴う建物等解体撤去工事（その４）",
      "支出額": 468.0
    },
    {
      "年度": 2014,
      "グループ": "B",
      "番号": 4,
      "支出先名": "あぶくま環境協業組合",
      "法人番号": null,
      "業務概要": "平成26年度（平成25年度繰越）南相馬市の対策地域内廃棄物（片付けごみ）運送業務",
      "支出額": 359.0
    },
    {
      "年度": 2014,
      "グループ": "B",
      "番号": 5,
      "支出先名": "庄司建設工業(株)",
      "法人番号": null,
      "業務概要": "平成26年度（平成25年度繰越）南相馬市警戒区域見直しに伴う建物等解体撤去工事（その２）",
      "支出額": 326.0
    },
    {
      "年度": 2014,
      "グループ": "B",
      "番号": 6,
      "支出先名": "遠野興産（株）",
      "法人番号": null,
      "業務概要": "平成26年度（平成25年度繰越）南相馬市内対策地域内廃棄物（木くず）処分等業務",
      "支出額": 304.0
    },
    {
      "年度": 2014,
      "グループ": "B",
      "番号": 7,
      "支出先名": "三井住友建設（株）",
      "法人番号": null,
      "業務概要": "平成25年度東日本大震災により生じた対策地域内廃棄物の国直轄処理業務（南相馬市小沢）における災害廃棄物仮置場整備工事（完成代金）",
      "支出額": 304.0
    },
    {
      "年度": 2014,
      "グループ": "B",
      "番号": 8,
      "支出先名": "中川企画建設(株)",
      "法人番号": null,
      "業務概要": "平成26年度（平成25年度繰越）南相馬市警戒区域見直しに伴う建物等解体撤去工事（その３）",
      "支出額": 137.0
    },
    {
      "年度": 2014,
      "グループ": "B",
      "番号": 9,
      "支出先名": "（株）中里工務店",
      "法人番号": null,
      "業務概要": "平成25年南相馬市警戒区域見直しに伴う廃棄物仮置場（大富地区）整備工事（完成代金）",
      "支出額": 130.0
    },
    {
      "年度": 2014,
      "グループ": "B",
      "番号": 10,
      "支出先名": "福島県南相馬市",
      "法人番号": null,
      "業務概要": "平成26年度南相馬市の警戒区域見直しに伴う廃棄物焼却等業務",
      "支出額": 96.0
    },
    {
      "年度": 2014,
      "グループ": "C",
      "番号": 1,
      "支出先名": "（株）安藤・間",
      "法人番号": null,
      "業務概要": "平成26年度東日本大震災により生じた対策地域内廃棄物の国直轄処理業務（双葉郡浪江町）における災害廃棄物収集・運搬・選別等業務",
      "支出額": 3753.0
    },
    {
      "年度": 2014,
      "グループ": "C",
      "番号": 2,
      "支出先名": "（株）安藤・間",
      "法人番号": null,
      "業務概要": "平成26年度東日本大震災により生じた対策地域内廃棄物の国直轄処理業務（浪江町請戸）における災害廃棄物仮置場整備工事",
      "支出額": 1692.0
    },
    {
      "年度": 2014,
      "グループ": "C",
      "番号": 3,
      "支出先名": "（株）安藤・間",
      "法人番号": null,
      "業務概要": "平成26年度東日本大震災により生じた対策地域内廃棄物の国直轄処理業務（浪江町棚塩）における災害廃棄物仮置場整備工事",
      "支出額": 961.0
    },
    {
      "年度": 2014,
      "グループ": "C",
      "番号": 4,
      "支出先名": "オカコー（株）",
      "法人番号": null,
      "業務概要": "平成26年度（平成25年度繰越）浪江町における建物等解体撤去工事（その２）",
      "支出額": 250.0
    },
    {
      "年度": 2014,
      "グループ": "C",
      "番号": 5,
      "支出先名": "双葉運輸(株)",
      "法人番号": null,
      "業務概要": "平成26年度（平成25年度繰越）浪江町の対策地域内廃棄物（片付けごみ）運送業務",
      "支出額": 216.0
    },
    {
      "年度": 2014,
      "グループ": "C",
      "番号": 6,
      "支出先名": "（株）高島テクノロジーセンター",
      "法人番号": null,
      "業務概要": "平成26年度（平成25年度繰越）浪江町における被災建物等解体関連受付・調査業務",
      "支出額": 84.0
    },
    {
      "年度": 2014,
      "グループ": "C",
      "番号": 7,
      "支出先名": "ハギハラ（株）",
      "法人番号": null,
      "業務概要": "平成26年度（平成25年度繰越）浪江町における建物等解体撤去工事",
      "支出額": 65.0
    },
    {
      "年度": 2014,
      "グループ": "C",
      "番号": 8,
      "支出先名": "東北ボーリング(株)",
      "法人番号": null,
      "業務概要": "平成25年度浪江町仮設処理施設建設予定地におけるさく井工事",
      "支出額": 35.0
    },
    {
      "年度": 2014,
      "グループ": "C",
      "番号": 9,
      "支出先名": "(有)アクツ",
      "法人番号": null,
      "業務概要": "平成26年度（平成25年度繰越）浪江町の避難指示区域見直しに伴い廃棄されるエアコン取外し等業務",
      "支出額": 25.0
    },
    {
      "年度": 2014,
      "グループ": "C",
      "番号": 10,
      "支出先名": "日立造船・安藤・間・神戸製鋼所特定共同企業体",
      "法人番号": null,
      "業務概要": "平成26年度浪江町対策地域内廃棄物処理業務（減容化処理）",
      "支出額": 12.0
    },
    {
      "年度": 2014,
      "グループ": "D",
      "番号": 1,
      "支出先名": "前田建設工業（株）",
      "法人番号": null,
      "業務概要": "平成26年度（平成25年度繰越）双葉町災害廃棄物等仮置場敷地造成工事",
      "支出額": 357.0
    },
    {
      "年度": 2014,
      "グループ": "D",
      "番号": 2,
      "支出先名": "前田建設工業（株）",
      "法人番号": null,
      "業務概要": "平成26年度（平成25年度繰越）双葉町における災害廃棄物収集・運搬等業務",
      "支出額": 58.0
    },
    {
      "年度": 2014,
      "グループ": "D",
      "番号": 3,
      "支出先名": "（有）佐洋運輸",
      "法人番号": null,
      "業務概要": "平成26年度（平成25年度繰越）双葉町の対策地域内廃棄物（片付けごみ）運送業務",
      "支出額": 12.0
    },
    {
      "年度": 2014,
      "グループ": "D",
      "番号": 4,
      "支出先名": "（株）田中",
      "法人番号": null,
      "業務概要": "平成26年度（平成25年度繰越）双葉町仮置場整備に係る排水路の堆積土砂等清掃業務",
      "支出額": 0.9
    },
    {
      "年度": 2014,
      "グループ": "D",
      "番号": 5,
      "支出先名": "エヌエス環境(株)",
      "法人番号": null,
      "業務概要": "平成26年度（平成25年度繰越）双葉町仮置場排水路における堆積土砂の放射能調査業務",
      "支出額": 0.3
    },
    {
      "年度": 2014,
      "グループ": "E",
      "番号": 1,
      "支出先名": "大林道路（株）",
      "法人番号": null,
      "業務概要": "平成25年大熊町警戒区域見直しに伴う廃棄物仮置場（大川原地区）整備工事（完成代金）",
      "支出額": 127.0
    },
    {
      "年度": 2014,
      "グループ": "E",
      "番号": 2,
      "支出先名": "双葉運輸(株)",
      "法人番号": null,
      "業務概要": "平成26年度（平成25年度繰越）大熊町の対策地域内廃棄物（片付けごみ）運送業務",
      "支出額": 70.0
    },
    {
      "年度": 2014,
      "グループ": "E",
      "番号": 3,
      "支出先名": "(有)アクツ",
      "法人番号": null,
      "業務概要": "平成26年度（平成25年度繰越）大熊町の避難指示区域見直しに伴い廃棄されるエアコン取外し等業務",
      "支出額": 3.0
    },
    {
      "年度": 2014,
      "グループ": "F",
      "番号": 1,
      "支出先名": "(株)丸東",
      "法人番号": null,
      "業務概要": "平成26年度（平成25年度繰越）富岡町の対策地域内廃棄物（片付けごみ）運送業務",
      "支出額": 648.0
    },
    {
      "年度": 2014,
      "グループ": "F",
      "番号": 2,
      "支出先名": "大林道路（株）",
      "法人番号": null,
      "業務概要": "平成25年度富岡町片付けごみ仮置場造成工事",
      "支出額": 257.0
    },
    {
      "年度": 2014,
      "グループ": "F",
      "番号": 3,
      "支出先名": "(株)倉伸",
      "法人番号": null,
      "業務概要": "平成26年度（平成25年度繰越）富岡町警戒区域見直しに伴う建物等解体撤去工事",
      "支出額": 151.0
    },
    {
      "年度": 2014,
      "グループ": "F",
      "番号": 4,
      "支出先名": "（株）高島テクノロジーセンター",
      "法人番号": null,
      "業務概要": "平成26年度（平成25年度繰越）富岡町における被災建物等解体関連受付・調査業務",
      "支出額": 103.0
    },
    {
      "年度": 2014,
      "グループ": "F",
      "番号": 5,
      "支出先名": "オカコー（株）",
      "法人番号": null,
      "業務概要": "平成26年度（平成25年度繰越）富岡町における被災特殊建築物解体撤去工事",
      "支出額": 55.0
    },
    {
      "年度": 2014,
      "グループ": "F",
      "番号": 6,
      "支出先名": "（株）丸東",
      "法人番号": null,
      "業務概要": "平成26年度（平成25年度繰越）富岡町における災害廃棄物収集・運搬等業務",
      "支出額": 44.0
    },
    {
      "年度": 2014,
      "グループ": "F",
      "番号": 7,
      "支出先名": "（株）倉伸",
      "法人番号": null,
      "業務概要": "平成26年度（平成25年度繰越）富岡町大字毛萱地内仮置場における津波被災建物等解体撤去工事",
      "支出額": 41.0
    },
    {
      "年度": 2014,
      "グループ": "F",
      "番号": 8,
      "支出先名": "一般社団法人福島県冷凍空調設備工業会",
      "法人番号": null,
      "業務概要": "平成26年度（平成25年度繰越）富岡町の避難指示区域見直しに伴い廃棄されるエアコン取外し等業務",
      "支出額": 36.0
    },
    {
      "年度": 2014,
      "グループ": "F",
      "番号": 9,
      "支出先名": "MHIEC・鹿島・MHI共同企業体",
      "法人番号": null,
      "業務概要": "平成26年度富岡町対策地域内廃棄物処理業務（破砕選別、減容化処理等） ",
      "支出額": 35.0
    },
    {
      "年度": 2014,
      "グループ": "F",
      "番号": 10,
      "支出先名": "（株）シマ商会",
      "法人番号": null,
      "業務概要": "平成26年度（平成25年度繰越）富岡町旧警戒区域内における廃自動車処分等業務",
      "支出額": 31.0
    },
    {
      "年度": 2014,
      "グループ": "G",
      "番号": 1,
      "支出先名": "前田・鴻池特定建設工事共同企業体",
      "法人番号": null,
      "業務概要": "平成26年度楢葉町警戒区域見直しに伴う建物等解体撤去工事",
      "支出額": 1418.0
    },
    {
      "年度": 2014,
      "グループ": "G",
      "番号": 2,
      "支出先名": "前田・鴻池特定建設工事共同企業体",
      "法人番号": null,
      "業務概要": "楢葉町追加対応除染等工事　＊対策地域内廃棄物分",
      "支出額": 950.0
    },
    {
      "年度": 2014,
      "グループ": "G",
      "番号": 3,
      "支出先名": "前田建設工業（株）",
      "法人番号": null,
      "業務概要": "平成26年度東日本大震災により生じた対策地域内廃棄物の国直轄処理業務（楢葉町前原）における家屋解体ごみ等仮置場整備工事",
      "支出額": 892.0
    },
    {
      "年度": 2014,
      "グループ": "G",
      "番号": 4,
      "支出先名": "前田・鴻池・大日本土木JV",
      "法人番号": null,
      "業務概要": "平成24年度楢葉町除染工事（その２）　＊対策地域内廃棄物分",
      "支出額": 705.0
    },
    {
      "年度": 2014,
      "グループ": "G",
      "番号": 5,
      "支出先名": "楢葉町建設業共同組合",
      "法人番号": null,
      "業務概要": "平成26年度（平成25年度繰越）楢葉町の対策地域内廃棄物（片付けごみ）運送業務",
      "支出額": 491.0
    },
    {
      "年度": 2014,
      "グループ": "G",
      "番号": 6,
      "支出先名": "前田建設工業（株）",
      "法人番号": null,
      "業務概要": "平成25年度東日本大震災により生じた対策地域内廃棄物の国直轄処理業務（楢葉町前原地区）における粗大ごみ等仮置場整備工事（完成払金）",
      "支出額": 130.0
    },
    {
      "年度": 2014,
      "グループ": "G",
      "番号": 7,
      "支出先名": "大林道路（株）",
      "法人番号": null,
      "業務概要": "平成26年度（平成25年度繰越）楢葉町前原第一仮置場撤去工事",
      "支出額": 87.0
    },
    {
      "年度": 2014,
      "グループ": "G",
      "番号": 8,
      "支出先名": "遠野興産（株）",
      "法人番号": null,
      "業務概要": "平成26年度（平成25年度繰越）楢葉町内対策地域内廃棄物（木くず）処分等業務",
      "支出額": 71.0
    },
    {
      "年度": 2014,
      "グループ": "G",
      "番号": 9,
      "支出先名": "公揚環境事業(有)",
      "法人番号": null,
      "業務概要": "平成26年度（平成25年度繰越）楢葉町の対策地域内廃棄物（浄化槽汚泥及び生し尿）収集運搬業務",
      "支出額": 17.0
    },
    {
      "年度": 2014,
      "グループ": "G",
      "番号": 10,
      "支出先名": "（株）同位体研究所",
      "法人番号": null,
      "業務概要": "平成26年度（平成25年度繰越）楢葉町内における浄化槽汚泥等放射能濃度測定業務",
      "支出額": 0.9
    },
    {
      "年度": 2014,
      "グループ": "H",
      "番号": 1,
      "支出先名": "神鋼環境・神戸製鋼共同企業体",
      "法人番号": null,
      "業務概要": "平成26年度飯舘村小宮地区対策地域内廃棄物処理業務（減容化処理）",
      "支出額": 3063.0
    },
    {
      "年度": 2014,
      "グループ": "H",
      "番号": 2,
      "支出先名": "IHI環境・日揮・熊谷組廃棄物等処理業務共同企業体",
      "法人番号": null,
      "業務概要": "平成26年度飯舘村蕨平地区対策地域内廃棄物等処理業務（減容化処理）",
      "支出額": 562.0
    },
    {
      "年度": 2014,
      "グループ": "H",
      "番号": 3,
      "支出先名": "斎藤運輸工業(株)",
      "法人番号": null,
      "業務概要": "平成26年度（平成25年度繰越）飯舘村の対策地域内廃棄物（片付けごみ）運送業務",
      "支出額": 286.0
    },
    {
      "年度": 2014,
      "グループ": "H",
      "番号": 4,
      "支出先名": "斎藤運輸工業(株)",
      "法人番号": null,
      "業務概要": "平成25年度飯舘村特殊建築物等解体撤去工事",
      "支出額": 37.0
    },
    {
      "年度": 2014,
      "グループ": "H",
      "番号": 5,
      "支出先名": "大成・熊谷・東急JV",
      "法人番号": null,
      "業務概要": "平成25年度飯舘村除染等工事（その１）　＊対策地域内廃棄物分",
      "支出額": 10.0
    },
    {
      "年度": 2014,
      "グループ": "I",
      "番号": 1,
      "支出先名": "大林道路（株）",
      "法人番号": null,
      "業務概要": "平成26年度東日本大震災により生じた対策地域内廃棄物の国直轄処理業務（川俣町山木屋）における片付けごみ等仮置場整備工事",
      "支出額": 485.0
    },
    {
      "年度": 2014,
      "グループ": "I",
      "番号": 2,
      "支出先名": "（有）川俣クリーンホープ　",
      "法人番号": null,
      "業務概要": "平成26年度（平成25年度繰越）川俣町山木屋地区の対策地域内廃棄物（片付けごみ）運送業務",
      "支出額": 57.0
    },
    {
      "年度": 2014,
      "グループ": "I",
      "番号": 3,
      "支出先名": "（株）川俣環境",
      "法人番号": null,
      "業務概要": "平成26年度（平成25年度繰越）川俣町の対策地域内廃棄物（浄化槽汚泥及び生し尿）収集運搬業務",
      "支出額": 2.0
    },
    {
      "年度": 2014,
      "グループ": "I",
      "番号": 4,
      "支出先名": "川俣方部衛生処理組合",
      "法人番号": null,
      "業務概要": "平成26年度（平成25年度繰越）川俣町の対策地域内廃棄物（浄化槽汚泥及び生し尿）処理業務",
      "支出額": 1.0
    },
    {
      "年度": 2014,
      "グループ": "I",
      "番号": 5,
      "支出先名": "(有)電修舎",
      "法人番号": null,
      "業務概要": "平成26年度（平成25年度繰越）川俣町の避難指示区域見直しに伴い廃棄されるエアコン取外し等業務",
      "支出額": 0.2
    },
    {
      "年度": 2014,
      "グループ": "J",
      "番号": 1,
      "支出先名": "奥村・西松・大豊JV",
      "法人番号": null,
      "業務概要": "平成24年度葛尾村除染工事　＊対策地域内廃棄物分",
      "支出額": 272.0
    },
    {
      "年度": 2014,
      "グループ": "J",
      "番号": 2,
      "支出先名": "(有)松本木材店",
      "法人番号": null,
      "業務概要": "平成26年度（平成25年度繰越）葛尾村の対策地域内廃棄物（片付けごみ）運送業務",
      "支出額": 51.0
    },
    {
      "年度": 2014,
      "グループ": "J",
      "番号": 3,
      "支出先名": "JFE・奥村・西松・大豊特定業務共同企業体",
      "法人番号": null,
      "業務概要": "平成26年度葛尾村対策地域内廃棄物処理業務（減容化処理）",
      "支出額": 19.0
    },
    {
      "年度": 2014,
      "グループ": "J",
      "番号": 4,
      "支出先名": "(株)アポロガス",
      "法人番号": null,
      "業務概要": "平成26年度（平成25年度繰越）葛尾村の避難指示区域見直しに伴い廃棄されるエアコン取外し等業務",
      "支出額": 0.1
    },
    {
      "年度": 2014,
      "グループ": "K",
      "番号": 1,
      "支出先名": "日立造船（株）",
      "法人番号": null,
      "業務概要": "平成26年度川内村対策地域内廃棄物処理業務（減容化処理）",
      "支出額": 670.0
    },
    {
      "年度": 2014,
      "グループ": "K",
      "番号": 2,
      "支出先名": "(株)鈴船建設",
      "法人番号": null,
      "業務概要": "平成26年度（平成25年度繰越）川内村警戒区域見直しに伴う建物等解体撤去工事",
      "支出額": 125.0
    },
    {
      "年度": 2014,
      "グループ": "K",
      "番号": 3,
      "支出先名": "(有)松本木材店",
      "法人番号": null,
      "業務概要": "平成26年度（平成25年度繰越）川内村の対策地域内廃棄物（農林系廃棄物）運送業務",
      "支出額": 24.0
    },
    {
      "年度": 2014,
      "グループ": "K",
      "番号": 4,
      "支出先名": "(株)丸東",
      "法人番号": null,
      "業務概要": "平成26年度（平成25年度繰越）川内村糠塚仮置場敷鉄板設置工事",
      "支出額": 16.0
    },
    {
      "年度": 2014,
      "グループ": "K",
      "番号": 5,
      "支出先名": "(株)三鋼",
      "法人番号": null,
      "業務概要": "平成26年度（平成25年度繰越）川内村の避難指示区域見直しに伴う金属くず処理等業務",
      "支出額": 0.5
    },
    {
      "年度": 2014,
      "グループ": "L",
      "番号": 1,
      "支出先名": "三和工業（株）",
      "法人番号": null,
      "業務概要": "平成25年度田村市警戒区域見直しに伴う建物等解体撤去工事（完成代金）",
      "支出額": 50.0
    },
    {
      "年度": 2014,
      "グループ": "L",
      "番号": 2,
      "支出先名": "富士工業（株）",
      "法人番号": null,
      "業務概要": "平成26年度（平成25年度繰越）田村市都路地区の対策地域内廃棄物（たい肥等）集積保管業務 ",
      "支出額": 2.0
    },
    {
      "年度": 2014,
      "グループ": "M",
      "番号": 1,
      "支出先名": "（株）エックス都市研究所",
      "法人番号": null,
      "業務概要": "指定廃棄物等処理支援業務",
      "支出額": 580.0
    },
    {
      "年度": 2014,
      "グループ": "N",
      "番号": 1,
      "支出先名": "（株）電通",
      "法人番号": null,
      "業務概要": "放射性物質汚染廃棄物等の処理に関する啓発普及等支援業務",
      "支出額": 661.0
    },
    {
      "年度": 2014,
      "グループ": "O",
      "番号": 1,
      "支出先名": "（株）エックス都市研究所",
      "法人番号": null,
      "業務概要": "指定廃棄物処分等有識者会議の運営補助業務",
      "支出額": 1.0
    },
    {
      "年度": 2014,
      "グループ": "P",
      "番号": 1,
      "支出先名": "パシフィックコンサルタンツ（株）",
      "法人番号": null,
      "業務概要": "放射性物質汚染廃棄物に関する安全対策検討会の運営補助業務",
      "支出額": 0.8
    },
    {
      "年度": 2014,
      "グループ": "Q",
      "番号": 1,
      "支出先名": "パシフィックコンサルタンツ（株）",
      "法人番号": null,
      "業務概要": "放射性物質汚染廃棄物に関する安全対策調査業務",
      "支出額": 7.0
    },
    {
      "年度": 2014,
      "グループ": "R",
      "番号": 1,
      "支出先名": "那須土木（株）",
      "法人番号": null,
      "業務概要": "指定廃棄物保管状況改善業務",
      "支出額": 130.0
    },
    {
      "年度": 2014,
      "グループ": "R",
      "番号": 2,
      "支出先名": "栃木県北建設業協同組合",
      "法人番号": null,
      "業務概要": "指定廃棄物保管状況改善業務",
      "支出額": 75.0
    },
    {
      "年度": 2014,
      "グループ": "R",
      "番号": 3,
      "支出先名": "（株）景観プランニング",
      "法人番号": null,
      "業務概要": "指定廃棄物保管場所敷地測量",
      "支出額": 0.8
    },
    {
      "年度": 2014,
      "グループ": "S",
      "番号": 1,
      "支出先名": "日本下水道事業団",
      "法人番号": null,
      "業務概要": "放射性物質を含む下水汚泥減容化施設解体調査委託業務",
      "支出額": 102.0
    },
    {
      "年度": 2014,
      "グループ": "T",
      "番号": 1,
      "支出先名": "日本下水道事業団",
      "法人番号": null,
      "業務概要": "放射性物質を含む下水汚泥減容化等調査業務",
      "支出額": 3664.0
    },
    {
      "年度": 2014,
      "グループ": "U",
      "番号": 1,
      "支出先名": "日立造船(株)",
      "法人番号": null,
      "業務概要": "放射性物質を含む農林業系副産物の焼却実証実験に係る調査業務",
      "支出額": 468.0
    },
    {
      "年度": 2014,
      "グループ": "V",
      "番号": 1,
      "支出先名": "（有） A",
      "法人番号": null,
      "業務概要": "平成２６年度指定廃棄物保管委託業務",
      "支出額": 30.0
    },
    {
      "年度": 2014,
      "グループ": "V",
      "番号": 2,
      "支出先名": "（株） B",
      "法人番号": null,
      "業務概要": "平成２６年度指定廃棄物保管委託業務",
      "支出額": 4.0
    },
    {
      "年度": 2014,
      "グループ": "V",
      "番号": 3,
      "支出先名": "（有） C",
      "法人番号": null,
      "業務概要": "平成２６年度指定廃棄物保管委託業務",
      "支出額": 2.0
    },
    {
      "年度": 2014,
      "グループ": "V",
      "番号": 4,
      "支出先名": "（株） D",
      "法人番号": null,
      "業務概要": "平成２６年度指定廃棄物保管委託業務",
      "支出額": 1.0
    },
    {
      "年度": 2014,
      "グループ": "W",
      "番号": 1,
      "支出先名": "いわき市",
      "法人番号": null,
      "業務概要": "平成２６年度指定廃棄物保管委託業務（いわき市）",
      "支出額": 181.0
    },
    {
      "年度": 2014,
      "グループ": "W",
      "番号": 2,
      "支出先名": "福島市",
      "法人番号": null,
      "業務概要": "平成２６年度指定廃棄物保管委託業務（金沢第二埋立処分場）",
      "支出額": 179.0
    },
    {
      "年度": 2014,
      "グループ": "W",
      "番号": 3,
      "支出先名": "柏市",
      "法人番号": null,
      "業務概要": "平成２６年度指定廃棄物保管委託業務（柏市清掃工場）",
      "支出額": 116.0
    },
    {
      "年度": 2014,
      "グループ": "W",
      "番号": 4,
      "支出先名": "那須町",
      "法人番号": null,
      "業務概要": "平成２５年度指定廃棄物保管委託業務（那須町（牧草等））",
      "支出額": 108.0
    },
    {
      "年度": 2014,
      "グループ": "W",
      "番号": 5,
      "支出先名": "那須塩原市",
      "法人番号": null,
      "業務概要": "平成２５年度指定廃棄物保管委託業務（那須塩原市（牧草等））",
      "支出額": 106.0
    },
    {
      "年度": 2014,
      "グループ": "W",
      "番号": 6,
      "支出先名": "柏市",
      "法人番号": null,
      "業務概要": "平成２６年度指定廃棄物保管委託業務（柏市第二清掃工場、柏市最終処分場）",
      "支出額": 78.0
    },
    {
      "年度": 2014,
      "グループ": "W",
      "番号": 7,
      "支出先名": "千葉県",
      "法人番号": null,
      "業務概要": "平成２６年度指定廃棄物保管委託業務（千葉県）",
      "支出額": 51.0
    },
    {
      "年度": 2014,
      "グループ": "W",
      "番号": 8,
      "支出先名": "白石市",
      "法人番号": null,
      "業務概要": "平成２６年度指定廃棄物保管委託業務（白石市）",
      "支出額": 44.0
    },
    {
      "年度": 2014,
      "グループ": "W",
      "番号": 9,
      "支出先名": "松戸市",
      "法人番号": null,
      "業務概要": "平成２６年度指定廃棄物保管委託業務（松戸市クリーンセンター、和名ヶ谷クリーンセンター）",
      "支出額": 42.0
    },
    {
      "年度": 2014,
      "グループ": "W",
      "番号": 10,
      "支出先名": "安達地方広域行政組合",
      "法人番号": null,
      "業務概要": "平成２６年度指定廃棄物保管委託業務（もとみやクリーンセンター、東和クリーンヒル）",
      "支出額": 31.0
    },
    {
      "年度": 2014,
      "グループ": "X",
      "番号": 1,
      "支出先名": "東京二十三区清掃一部事務組合",
      "法人番号": null,
      "業務概要": "廃棄物処理施設モニタリング事業費補助金",
      "支出額": 10.0
    },
    {
      "年度": 2014,
      "グループ": "X",
      "番号": 2,
      "支出先名": "所沢市",
      "法人番号": null,
      "業務概要": "廃棄物処理施設モニタリング事業費補助金",
      "支出額": 9.0
    },
    {
      "年度": 2014,
      "グループ": "X",
      "番号": 3,
      "支出先名": "いわき市",
      "法人番号": null,
      "業務概要": "廃棄物処理施設モニタリング事業費補助金",
      "支出額": 7.0
    },
    {
      "年度": 2014,
      "グループ": "X",
      "番号": 4,
      "支出先名": "川越市",
      "法人番号": null,
      "業務概要": "廃棄物処理施設モニタリング事業費補助金",
      "支出額": 7.0
    },
    {
      "年度": 2014,
      "グループ": "X",
      "番号": 5,
      "支出先名": "一関地区広域行政組合",
      "法人番号": null,
      "業務概要": "廃棄物処理施設モニタリング事業費補助金",
      "支出額": 6.0
    },
    {
      "年度": 2014,
      "グループ": "X",
      "番号": 6,
      "支出先名": "南相馬市",
      "法人番号": null,
      "業務概要": "廃棄物処理施設モニタリング事業費補助金",
      "支出額": 6.0
    },
    {
      "年度": 2014,
      "グループ": "X",
      "番号": 7,
      "支出先名": "福島市",
      "法人番号": null,
      "業務概要": "廃棄物処理施設モニタリング事業費補助金",
      "支出額": 6.0
    },
    {
      "年度": 2014,
      "グループ": "X",
      "番号": 8,
      "支出先名": "高崎市",
      "法人番号": null,
      "業務概要": "廃棄物処理施設モニタリング事業費補助金",
      "支出額": 5.0
    },
    {
      "年度": 2014,
      "グループ": "X",
      "番号": 9,
      "支出先名": "松戸市",
      "法人番号": null,
      "業務概要": "廃棄物処理施設モニタリング事業費補助金",
      "支出額": 5.0
    },
    {
      "年度": 2014,
      "グループ": "X",
      "番号": 10,
      "支出先名": "一般財団法人茨城県環境保全事業団",
      "法人番号": null,
      "業務概要": "廃棄物処理施設モニタリング事業費補助金",
      "支出額": 5.0
    },
    {
      "年度": 2014,
      "グループ": "Y",
      "番号": 1,
      "支出先名": "相馬市",
      "法人番号": null,
      "業務概要": "平成26年度放射性物質汚染廃棄物処理加速化事業",
      "支出額": 41.0
    },
    {
      "年度": 2014,
      "グループ": "Y",
      "番号": 2,
      "支出先名": "一関市",
      "法人番号": null,
      "業務概要": "平成26年度放射性物質汚染廃棄物処理加速化事業",
      "支出額": 40.0
    },
    {
      "年度": 2014,
      "グループ": "Y",
      "番号": 3,
      "支出先名": "宮古地区広域行政組合",
      "法人番号": null,
      "業務概要": "平成26年度放射性物質汚染廃棄物処理加速化事業",
      "支出額": 28.0
    },
    {
      "年度": 2014,
      "グループ": "Y",
      "番号": 4,
      "支出先名": "山田町",
      "法人番号": null,
      "業務概要": "平成26年度放射性物質汚染廃棄物処理加速化事業",
      "支出額": 23.0
    },
    {
      "年度": 2014,
      "グループ": "Y",
      "番号": 5,
      "支出先名": "奥州市",
      "法人番号": null,
      "業務概要": "平成26年度放射性物質汚染廃棄物処理加速化事業",
      "支出額": 21.0
    },
    {
      "年度": 2014,
      "グループ": "Y",
      "番号": 6,
      "支出先名": "遠野市",
      "法人番号": null,
      "業務概要": "平成26年度放射性物質汚染廃棄物処理加速化事業",
      "支出額": 16.0
    },
    {
      "年度": 2014,
      "グループ": "Y",
      "番号": 7,
      "支出先名": "北上市",
      "法人番号": null,
      "業務概要": "平成26年度放射性物質汚染廃棄物処理加速化事業",
      "支出額": 7.0
    },
    {
      "年度": 2014,
      "グループ": "Y",
      "番号": 8,
      "支出先名": "奥州金ケ崎行政事務組合",
      "法人番号": null,
      "業務概要": "平成26年度放射性物質汚染廃棄物処理加速化事業",
      "支出額": 6.0
    },
    {
      "年度": 2014,
      "グループ": "Y",
      "番号": 9,
      "支出先名": "岩手・玉山環境組合",
      "法人番号": null,
      "業務概要": "平成26年度放射性物質汚染廃棄物処理加速化事業",
      "支出額": 4.0
    },
    {
      "年度": 2014,
      "グループ": "Y",
      "番号": 10,
      "支出先名": "金ケ崎町",
      "法人番号": null,
      "業務概要": "平成26年度放射性物質汚染廃棄物処理加速化事業",
      "支出額": 4.0
    },
    {
      "年度": 2014,
      "グループ": "Z",
      "番号": 1,
      "支出先名": "個人等",
      "法人番号": null,
      "業務概要": "仮置場の土地の補償等",
      "支出額": 373.0
    },
    {
      "年度": 2014,
      "グループ": "a",
      "番号": 1,
      "支出先名": "個人等",
      "法人番号": null,
      "業務概要": "放射性物質汚染対処特別措置法に基づき、特定廃棄物の処理に必要な事務費",
      "支出額": 55.0
    }
  ],
  "アウトカム": [
    {
      "成果目標": "対策地域内廃棄物処理\n　避難指示解除準備区域及び居住制限区域における帰還の妨げとなる廃棄物を撤去し、仮置場への搬入を完了する。",
      "成果指標": "帰還の妨げとなる廃棄物を撤去し、仮置場への搬入が完了した市町村数。",
      "単位": "市町村数（累計）",
      "目標値": "10",
      "目標最終年度": null,
      "成果実績": [
        {
          "年度": 2012,
          "成果実績": null,
          "目標値": null
        },
        {
          "年度": 2013,
          "成果実績": 3.0,
          "目標値": 3.0
        },
        {
          "年度": 2014,
          "成果実績": 6.0,
          "目標値": 8.0
        }
      ]
    }
  ],
  "定量的な目標が設定できない理由": null,
  "アウトプット": [
    {
      "活動指標": "対策地域内廃棄物処理・指定廃棄物処理\n　　→仮置場の確保及び仮設処理施設の設置数\n※活動実績は、仮置場・仮設処理施設の整備状況を記載。",
      "単位": "箇所\n（累計）",
      "活動実績": [
        {
          "年度": 2012,
          "活動実績": 6.0,
          "当初見込み": 36.0
        },
        {
          "年度": 2013,
          "活動実績": 16.0,
          "当初見込み": 36.0
        },
        {
          "年度": 2014,
          "活動実績": 30.0,
          "当初見込み": 36.0
        }
      ]
    }
  ],
  "url": "https://www.reconstruction.go.jp/topics/main-cat8/sub-cat8-3/reviewsheet_h27/sh/26021900_fukkochou.xlsx",
  "関連する過去のレビューシート": []
}