{
  "ID": 14501,
  "事業ID": 1441,
  "公開年度": 2017,
  "事業名": "下水道事業",
  "開始年度": 1957,
  "終了年度": null,
  "府省庁": "国土交通省",
  "事業番号1": null,
  "事業番号2": "0059",
  "事業番号3": null,
  "担当部局庁": "水管理・国土保全局　下水道部",
  "担当課室": "下水道事業課",
  "作成責任者": "課長　加藤　裕之",
  "会計区分": [
    "一般会計"
  ],
  "事業目的": "①し尿、生活雑排水などの汚水の排除・処理による公衆衛生の向上、生活環境の改善、河川などの公共用水域の水質保全\n②バイオマスである下水汚泥等の有効利用による低炭素社会、循環型社会の構築\n③集中豪雨による浸水被害の軽減",
  "事業概要": "○地方公共団体が実施する下記事業に対する補助金。※（）は補助率\n　①民間活力イノベーション推進下水道事業費補助・・・再生可能エネルギーの利用促進及び効率的な下水道整備等を図るため、PPP/PFI事業などの官民連携事業を支援（1/2、5.5/10等）\n　②未普及解消下水道事業費補助・・・公衆衛生の向上、生活環境の改善を図るため、し尿・生活雑排水などの汚水の排除を行うための汚水管の整備等（1/2等）\n　③浸水対策下水道事業費補助・・・集中豪雨による浸水被害の軽減を図るため、官民連携した雨水管、ポンプ場、雨水調整池の整備等（1/2等）\n○下水道事業の計画的かつ効率的な推進を図るために必要な国が実施する調査研究",
  "実施方法": [
    "直接実施",
    "委託・請負",
    "補助"
  ],
  "主要施策": [
    "国土強靱化施策",
    "地方創生"
  ],
  "予算": [
    {
      "年度": 2014,
      "当初予算": 5225.0,
      "補正予算": 0.0,
      "前年度から繰越し": 1087.0,
      "翌年度へ繰越し": -724.0,
      "予備費等": 0.0,
      "予算計": 5588.0,
      "執行額": 5466.0
    },
    {
      "年度": 2015,
      "当初予算": 5251.0,
      "補正予算": 0.0,
      "前年度から繰越し": 724.0,
      "翌年度へ繰越し": -655.0,
      "予備費等": 0.0,
      "予算計": 5320.0,
      "執行額": 5157.0
    },
    {
      "年度": 2016,
      "当初予算": 5280.0,
      "補正予算": 0.0,
      "前年度から繰越し": 655.0,
      "翌年度へ繰越し": -220.0,
      "予備費等": 0.0,
      "予算計": 5715.0,
      "執行額": 5532.0
    },
    {
      "年度": 2017,
      "当初予算": 5284.0,
      "補正予算": 0.0,
      "前年度から繰越し": 220.0,
      "翌年度へ繰越し": 0.0,
      "予備費等": 0.0,
      "予算計": 5504.0
    },
    {
      "年度": 2018,
      "要求額": 6199.0
    }
  ],
  "支出先": [
    {
      "年度": 2016,
      "グループ": "A",
      "番号": 1,
      "支出先名": "静岡市",
      "法人番号": "8000020221007",
      "業務概要": "下水道事業施設の整備等を実施",
      "支出額": 883.0,
      "": true
    },
    {
      "年度": 2016,
      "グループ": "A",
      "番号": 2,
      "支出先名": "愛知県",
      "法人番号": "1000020230006",
      "業務概要": "下水道事業施設の整備等を実施",
      "支出額": 516.0,
      "": true
    },
    {
      "年度": 2016,
      "グループ": "A",
      "番号": 3,
      "支出先名": "日本下水道事業団",
      "法人番号": "2011105003406",
      "業務概要": "下水道事業施設の整備等を実施",
      "支出額": 129.0,
      "": true
    },
    {
      "年度": 2016,
      "グループ": "A",
      "番号": 4,
      "支出先名": "福岡市",
      "法人番号": "3000020401307",
      "業務概要": "下水道事業施設の整備等を実施",
      "支出額": 127.0,
      "": true
    },
    {
      "年度": 2016,
      "グループ": "A",
      "番号": 5,
      "支出先名": "横浜市",
      "法人番号": "3000020141003",
      "業務概要": "下水道事業施設の整備等を実施",
      "支出額": 84.0,
      "": true
    },
    {
      "年度": 2016,
      "グループ": "A",
      "番号": 6,
      "支出先名": "秋田県",
      "法人番号": "1000020050008",
      "業務概要": "下水道事業施設の整備等を実施",
      "支出額": 26.0,
      "": true
    },
    {
      "年度": 2016,
      "グループ": "B",
      "番号": 1,
      "支出先名": "水管理・国土保全局",
      "法人番号": "2000012100001",
      "業務概要": "全国的な下水道事業の課題・あり方についての調査・検討",
      "支出額": 567.0,
      "": true
    },
    {
      "年度": 2016,
      "グループ": "C",
      "番号": 1,
      "支出先名": "北陸地方整備局",
      "法人番号": "2000012100001",
      "業務概要": "各地域における下水道事業の課題・あり方についての調査・検討",
      "支出額": 34.0,
      "": true
    },
    {
      "年度": 2016,
      "グループ": "C",
      "番号": 2,
      "支出先名": "中国地方整備局",
      "法人番号": "2000012100001",
      "業務概要": "各地域における下水道事業の課題・あり方についての調査・検討",
      "支出額": 31.0,
      "": true
    },
    {
      "年度": 2016,
      "グループ": "C",
      "番号": 3,
      "支出先名": "中部地方整備局",
      "法人番号": "2000012100001",
      "業務概要": "各地域における下水道事業の課題・あり方についての調査・検討",
      "支出額": 25.0,
      "": true
    },
    {
      "年度": 2016,
      "グループ": "C",
      "番号": 4,
      "支出先名": "北海道開発局",
      "法人番号": "2000012100001",
      "業務概要": "各地域における下水道事業の課題・あり方についての調査・検討",
      "支出額": 9.0,
      "": true
    },
    {
      "年度": 2016,
      "グループ": "C",
      "番号": 5,
      "支出先名": "九州地方整備局",
      "法人番号": "2000012100001",
      "業務概要": "各地域における下水道事業の課題・あり方についての調査・検討",
      "支出額": 8.0,
      "": true
    },
    {
      "年度": 2016,
      "グループ": "C",
      "番号": 6,
      "支出先名": "東北地方整備局",
      "法人番号": "2000012100001",
      "業務概要": "各地域における下水道事業の課題・あり方についての調査・検討",
      "支出額": 8.0,
      "": true
    },
    {
      "年度": 2016,
      "グループ": "C",
      "番号": 7,
      "支出先名": "四国地方整備局",
      "法人番号": "2000012100001",
      "業務概要": "各地域における下水道事業の課題・あり方についての調査・検討",
      "支出額": 2.0,
      "": true
    },
    {
      "年度": 2016,
      "グループ": "D",
      "番号": 1,
      "支出先名": "国土技術政策総合研究所",
      "法人番号": "2000012100001",
      "業務概要": "下水道事業における諸課題のうち、特に技術開発や技術基準に係る調査・検討",
      "支出額": 3083.0,
      "": true
    },
    {
      "年度": 2016,
      "グループ": "E",
      "番号": 1,
      "支出先名": "ＰｗＣアドバイザリー・東京設計共同提案体",
      "法人番号": "7010001067262",
      "業務概要": "下水汚泥の有効利用等における官民連携事業の導入に関する検討業務",
      "支出額": 25.0,
      "": true
    },
    {
      "年度": 2016,
      "グループ": "E",
      "番号": 2,
      "支出先名": "（株）建設技術研究所",
      "法人番号": "7010001042703",
      "業務概要": "健全な水・物質循環の構築に向けたBISTRO下水道等推進方策検討業務",
      "支出額": 22.0,
      "": true
    },
    {
      "年度": 2016,
      "グループ": "E",
      "番号": 3,
      "支出先名": "三菱総合研究所・総合設備コンサルタント共同提案体",
      "法人番号": "6010001030403",
      "業務概要": "下水熱利用事業導入支援等業務",
      "支出額": 15.0,
      "": true
    },
    {
      "年度": 2016,
      "グループ": "E",
      "番号": 4,
      "支出先名": "三菱化工機（株）",
      "法人番号": "7020001074662",
      "業務概要": "下水バイオガスによる水素創エネ技術の普及展開戦略検討業務",
      "支出額": 15.0,
      "": true
    },
    {
      "年度": 2016,
      "グループ": "E",
      "番号": 5,
      "支出先名": "国立大学法人　山形大学",
      "法人番号": "8390005002565",
      "業務概要": "下水処理水再利用による飼料用米栽培に関する研究",
      "支出額": 8.0,
      "": true
    },
    {
      "年度": 2016,
      "グループ": "E",
      "番号": 6,
      "支出先名": "日本水工設計（株）",
      "法人番号": "4010001062217",
      "業務概要": "平成２８年度　下水汚泥等の資源有効利用状況に関する調査業務",
      "支出額": 7.0,
      "": true
    },
    {
      "年度": 2016,
      "グループ": "E",
      "番号": 7,
      "支出先名": "（公社）土木学会",
      "法人番号": "5011105004847",
      "業務概要": "下水道資源の利活用に資する技術開発促進検討業務",
      "支出額": 7.0,
      "": true
    },
    {
      "年度": 2016,
      "グループ": "E",
      "番号": 8,
      "支出先名": "(公財）日本下水道新技術機構",
      "法人番号": "4011105003503",
      "業務概要": "下水道分野における技術開発促進検討業務",
      "支出額": 7.0,
      "": true
    },
    {
      "年度": 2016,
      "グループ": "E",
      "番号": 9,
      "支出先名": "鹿児島工業高等専門学校",
      "法人番号": "8010105000820",
      "業務概要": "下水汚泥を用いた高付加価値きのこの生産技術及びその生産過程で発生する廃培地・炭酸ガスの高度利用技術の開発",
      "支出額": 5.0,
      "": true
    },
    {
      "年度": 2016,
      "グループ": "E",
      "番号": 10,
      "支出先名": "岐阜大学",
      "法人番号": "5200005002181",
      "業務概要": "微生物燃料電池による省エネ型廃水処理のための基盤技術の開発",
      "支出額": 5.0,
      "": true
    },
    {
      "年度": 2016,
      "グループ": "F",
      "番号": 1,
      "支出先名": "(公財）日本下水道新技術機構・(株)日水コン共同提案体",
      "法人番号": "4011105003503",
      "業務概要": "下水道管渠内水位情報等を活用した効率的浸水対策検討業務",
      "支出額": 40.0,
      "": true
    },
    {
      "年度": 2016,
      "グループ": "F",
      "番号": 2,
      "支出先名": "(株)日水コン",
      "法人番号": "3011101015783",
      "業務概要": "新たな雨水管理計画に関する指針作成等検討業務",
      "支出額": 19.0,
      "": true
    },
    {
      "年度": 2016,
      "グループ": "F",
      "番号": 3,
      "支出先名": "（公財）日本下水道新技術機構",
      "法人番号": "4011105003503",
      "業務概要": "下水道による浸水対策に資する情報利活用検討業務",
      "支出額": 20.0,
      "": true
    },
    {
      "年度": 2016,
      "グループ": "F",
      "番号": 4,
      "支出先名": "（公財）日本下水道新技術機構",
      "法人番号": "4011105003503",
      "業務概要": "気候変動が下水道管渠へ及ぼす影響に対する産官学連携による対応方策検討業務",
      "支出額": 15.0,
      "": true
    },
    {
      "年度": 2016,
      "グループ": "F",
      "番号": 5,
      "支出先名": "（株）ニュージェック・（一財）都市技術センター共同提案体",
      "法人番号": "2120001086883",
      "業務概要": "下水道施設における河川との一体的な運用による浸水対策手法検討業務",
      "支出額": 10.0,
      "": true
    },
    {
      "年度": 2016,
      "グループ": "F",
      "番号": 6,
      "支出先名": "特定非営利活動法人　日本トイレ研究所",
      "法人番号": "7010405008309",
      "業務概要": "下水道に関する防災教育推進手法検討業務",
      "支出額": 10.0,
      "": true
    },
    {
      "年度": 2016,
      "グループ": "F",
      "番号": 7,
      "支出先名": "土木研究所",
      "法人番号": "8050005005206",
      "業務概要": "河川・下水道のシームレスモデルを用いたリアルタイム浸水予測手法の開発",
      "支出額": 5.0,
      "": true
    },
    {
      "年度": 2016,
      "グループ": "F",
      "番号": 8,
      "支出先名": "九州大学",
      "法人番号": "3290005003743",
      "業務概要": "都市型水害軽減に向けた土壌改良による流出抑制技術の構築",
      "支出額": 5.0,
      "": true
    },
    {
      "年度": 2016,
      "グループ": "F",
      "番号": 9,
      "支出先名": "（株）東京設計事務所",
      "法人番号": "6010001034247",
      "業務概要": "雨水公共下水道の推進に係る検討会開催支援業務",
      "支出額": 1.0,
      "": true
    },
    {
      "年度": 2016,
      "グループ": "F",
      "番号": 10,
      "支出先名": "（公財）日本下水道新技術機構",
      "法人番号": "4011105003503",
      "業務概要": "地震発生後における下水道機能の早期復旧手法検討資料作成補助業務",
      "支出額": 1.0,
      "": true
    },
    {
      "年度": 2016,
      "グループ": "G",
      "番号": 1,
      "支出先名": "（株）建設技術研究所",
      "法人番号": "7010001042703",
      "業務概要": "水環境に係る技術開発体系化等検討業務",
      "支出額": 20.0,
      "": true
    },
    {
      "年度": 2016,
      "グループ": "G",
      "番号": 2,
      "支出先名": "（公財）日本下水道新技術機構",
      "法人番号": "4011105003503",
      "業務概要": "ＩＣＴ等を活用した段階的高度処理等推進方策検討業務",
      "支出額": 20.0,
      "": true
    },
    {
      "年度": 2016,
      "グループ": "G",
      "番号": 3,
      "支出先名": "（株）建設技術研究所",
      "法人番号": "7010001042703",
      "業務概要": "適切な雨天時水質管理の推進に係る検討業務",
      "支出額": 15.0,
      "": true
    },
    {
      "年度": 2016,
      "グループ": "G",
      "番号": 4,
      "支出先名": "（株）日水コン　東京支所",
      "法人番号": "3011101015783",
      "業務概要": "産学官が連携した東京湾の水質改善方策検討業務",
      "支出額": 15.0,
      "": true
    },
    {
      "年度": 2016,
      "グループ": "G",
      "番号": 5,
      "支出先名": "（株）日水コン　東京支所",
      "法人番号": "3011101015783",
      "業務概要": "能動的水環境管理推進方策検討業務",
      "支出額": 15.0,
      "": true
    },
    {
      "年度": 2016,
      "グループ": "G",
      "番号": 6,
      "支出先名": "（株）日水コン　東京支所",
      "法人番号": "3011101015783",
      "業務概要": "下水道における水系水質リスク低減に向けた対応方策検討業務",
      "支出額": 15.0,
      "": true
    },
    {
      "年度": 2016,
      "グループ": "G",
      "番号": 7,
      "支出先名": "鹿児島大学",
      "法人番号": "6340005001879",
      "業務概要": "下水処理水中の生態影響原因物質を対象とした高効率汎用型探索技術の開発",
      "支出額": 10.0,
      "": true
    },
    {
      "年度": 2016,
      "グループ": "G",
      "番号": 8,
      "支出先名": "国際航業（株）東京支店",
      "法人番号": "9010001008669",
      "業務概要": "下水道を核とした市民科学育成プロジェクト推進方策検討業務",
      "支出額": 8.0,
      "": true
    },
    {
      "年度": 2016,
      "グループ": "G",
      "番号": 9,
      "支出先名": "広島大学大学院",
      "法人番号": "1240005004054",
      "業務概要": "雨天時に市街地から流出するノンポイント汚濁負荷量の予測モデル開発",
      "支出額": 5.0,
      "": true
    },
    {
      "年度": 2016,
      "グループ": "G",
      "番号": 10,
      "支出先名": "日本水工設計（株）・（一財）造水促進センター共同提案体",
      "法人番号": "4010001062217",
      "業務概要": "紫外線等を活用した下水消毒技術等に関する調査検討業務",
      "支出額": 5.0,
      "": true
    },
    {
      "年度": 2016,
      "グループ": "H",
      "番号": 1,
      "支出先名": "日本下水道事業団",
      "法人番号": "2011105003406",
      "業務概要": "下水道事業における適正な積算基準の制定に関する検討業務",
      "支出額": 20.0,
      "": true
    },
    {
      "年度": 2016,
      "グループ": "H",
      "番号": 2,
      "支出先名": "（株）日水コン・メタウォーター（株）・国際航業（株）共同提案体",
      "法人番号": "3011101015783",
      "業務概要": "持続可能な下水道事業実施に係る検討を踏まえた対応策の実現に関する業務",
      "支出額": 14.0,
      "": true
    },
    {
      "年度": 2016,
      "グループ": "H",
      "番号": 3,
      "支出先名": "（公財）日本下水道新技術機構",
      "法人番号": "4011105003503",
      "業務概要": "下水道管きょ空間利活用に関する調査検討業務",
      "支出額": 10.0,
      "": true
    },
    {
      "年度": 2016,
      "グループ": "H",
      "番号": 4,
      "支出先名": "日本水工設計・アビームコンサルティング共同提案体",
      "法人番号": "4010001062217",
      "業務概要": "ベンチマーク手法による下水道の適切な事業運営の確立方策検討業務",
      "支出額": 10.0,
      "": true
    },
    {
      "年度": 2016,
      "グループ": "H",
      "番号": 5,
      "支出先名": "(株)日水コン",
      "法人番号": "3011101015783",
      "業務概要": "官民連携事業を活用した下水道普及促進検討業務",
      "支出額": 10.0,
      "": true
    },
    {
      "年度": 2016,
      "グループ": "H",
      "番号": 6,
      "支出先名": "（株）日水コン東京支所",
      "法人番号": "3011101015783",
      "業務概要": "下水道事業の効果分析検討業務",
      "支出額": 10.0,
      "": true
    },
    {
      "年度": 2016,
      "グループ": "H",
      "番号": 7,
      "支出先名": "（公財）日本下水道新技術機構",
      "法人番号": "4011105003503",
      "業務概要": "下水処理場における水処理二軸管理方策検討業務",
      "支出額": 9.0,
      "": true
    },
    {
      "年度": 2016,
      "グループ": "H",
      "番号": 8,
      "支出先名": "国立大学法人岐阜大学・国立大学法人名古屋大学・公益財団法人日本下水道新技術機構　共同提案体",
      "法人番号": "5200005002181",
      "業務概要": "下水道事業における臭気抑制効果に関する調査検討業務",
      "支出額": 7.0,
      "": true
    },
    {
      "年度": 2016,
      "グループ": "H",
      "番号": 9,
      "支出先名": "（株）日水コン東京支所",
      "法人番号": "3011101015783",
      "業務概要": "効率的な下水道事業実施に向けた事業量分析業務",
      "支出額": 7.0,
      "": true
    },
    {
      "年度": 2016,
      "グループ": "H",
      "番号": 10,
      "支出先名": "北海道大学大学院工学研究院",
      "法人番号": "6430005004014",
      "業務概要": "執行体制の脆弱化に対応した下水処理水中の細菌・ウィルスの簡易分析技術の開発",
      "支出額": 5.0,
      "": true
    }
  ],
  "アウトカム": [
    {
      "成果目標": "平成32年度までに下水汚泥エネルギー化率を約30%まで引き上げる。",
      "成果指標": "下水汚泥エネルギー化率",
      "単位": "％",
      "目標値": "30",
      "目標最終年度": 2020,
      "成果実績": [
        {
          "年度": 2014,
          "成果実績": 15.0,
          "目標値": null
        },
        {
          "年度": 2015,
          "成果実績": 16.0,
          "目標値": null
        },
        {
          "年度": 2016,
          "成果実績": null,
          "目標値": null
        }
      ]
    },
    {
      "成果目標": "平成32年度までに高度処理実施率を約60％まで引き上げる。",
      "成果指標": "良好な水環境創出のための高度処理実施率",
      "単位": "％",
      "目標値": "60",
      "目標最終年度": 2020,
      "成果実績": [
        {
          "年度": 2014,
          "成果実績": 44.0,
          "目標値": null
        },
        {
          "年度": 2015,
          "成果実績": 46.0,
          "目標値": null
        },
        {
          "年度": 2016,
          "成果実績": null,
          "目標値": null
        }
      ]
    },
    {
      "成果目標": "平成32年度までに都市浸水対策達成率を約62％まで引き上げる。",
      "成果指標": "下水道による都市浸水対策達成率",
      "単位": "％",
      "目標値": "62",
      "目標最終年度": 2020,
      "成果実績": [
        {
          "年度": 2014,
          "成果実績": 56.0,
          "目標値": null
        },
        {
          "年度": 2015,
          "成果実績": 57.0,
          "目標値": null
        },
        {
          "年度": 2016,
          "成果実績": 58.0,
          "目標値": null
        }
      ]
    },
    {
      "成果目標": "平成32年度までに汚水処理人口普及率を約96%まで引き上げる。",
      "成果指標": "汚水処理人口普及率",
      "単位": "％",
      "目標値": "96",
      "目標最終年度": 2020,
      "成果実績": [
        {
          "年度": 2014,
          "成果実績": 89.0,
          "目標値": null
        },
        {
          "年度": 2015,
          "成果実績": 90.0,
          "目標値": null
        },
        {
          "年度": 2016,
          "成果実績": 90.0,
          "目標値": null
        }
      ]
    }
  ],
  "定量的な目標が設定できない理由": null,
  "アウトプット": [
    {
      "活動指標": "都道府県・市町村における汚泥エネルギー化等下水道事業実施箇所数\n（下水道事業費補助の補助金等により下水汚泥のエネルギー化等に係る施設整備が実施された箇所）",
      "単位": "箇所",
      "活動実績": [
        {
          "年度": 2014,
          "活動実績": 2.0,
          "当初見込み": 2.0
        },
        {
          "年度": 2015,
          "活動実績": 6.0,
          "当初見込み": 6.0
        },
        {
          "年度": 2016,
          "活動実績": 7.0,
          "当初見込み": 7.0
        }
      ]
    },
    {
      "活動指標": "B-DASH採択案件数（下水汚泥エネルギー化等の一層の効率化等に資する実証事業採択箇所数）",
      "単位": "箇所",
      "活動実績": [
        {
          "年度": 2014,
          "活動実績": 6.0,
          "当初見込み": 6.0
        },
        {
          "年度": 2015,
          "活動実績": 9.0,
          "当初見込み": 9.0
        },
        {
          "年度": 2016,
          "活動実績": 4.0,
          "当初見込み": 4.0
        }
      ]
    }
  ],
  "url": "http://www.mlit.go.jp/common/001199562.xlsx"
}