{
  "ID": 28041,
  "事業ID": 11637,
  "url": null,
  "公開年度": 2020,
  "事業名": "モントリオール議定書多数国間基金拠出金（HFC分)（ODA)",
  "開始年度": 2019,
  "終了年度": null,
  "府省庁": "環境省",
  "事業番号1": null,
  "事業番号2": "0096",
  "事業番号3": null,
  "担当部局庁": "地球環境局",
  "担当課室": "地球温暖化対策課\nフロン対策室",
  "作成責任者": "室長　豊住　朝子",
  "会計区分": [
    "一般会計"
  ],
  "事業目的": "「オゾン層を破壊する物質に関するモントリオール議定書」は、オゾン層を破壊する恐れのある物質（いわゆる特定フロン）の生産・消費の規制を行うことを目的としており、先進国は同議定書の多数国間基金を通じ、開発途上国における特定フロンの削減スケジュールの遵守を支援してきた。平成28年10月、温室効果が高い代替フロンHFCを規制対象物質に追加する議定書改正が採択され、平成30年12月に我が国も締結した。改正議定書は平成31年1月1日に発効したところ、開発途上国が削減スケジュールを着実に遵守できるよう、多数国間基金を通じて対策を支援する。　",
  "事業概要": "モントリオール議定書第10 条に基づく多数国間基金のうち、議定書HFC改正をうけ同基金に追加することとなる、開発途上国のHFC削減のための対策分に係る拠出金のうち、環境省として負担すべき部分に関するもの。",
  "実施方法": [
    "その他"
  ],
  "主要施策": [
    "地球温暖化対策",
    "ＯＤＡ"
  ],
  "予算": [
    {
      "年度": 2017,
      "当初予算": 0.0,
      "補正予算": 0.0,
      "前年度から繰越し": 0.0,
      "翌年度へ繰越し": 0.0,
      "予備費等": 0.0,
      "予算計": 0.0,
      "執行額": 0.0
    },
    {
      "年度": 2018,
      "当初予算": 0.0,
      "補正予算": 0.0,
      "前年度から繰越し": 0.0,
      "翌年度へ繰越し": 0.0,
      "予備費等": 0.0,
      "予算計": 0.0,
      "執行額": 0.0
    },
    {
      "年度": 2019,
      "当初予算": 24.0,
      "補正予算": 0.0,
      "前年度から繰越し": 0.0,
      "翌年度へ繰越し": 0.0,
      "予備費等": 0.0,
      "予算計": 24.0,
      "執行額": 24.0
    },
    {
      "年度": 2020,
      "当初予算": 24.0,
      "補正予算": 0.0,
      "前年度から繰越し": 0.0,
      "翌年度へ繰越し": 0.0,
      "予備費等": 0.0,
      "予算計": 24.0
    },
    {
      "年度": 2021,
      "要求額": 24.0
    }
  ],
  "支出先": [
    {
      "年度": 2019,
      "グループ": "A",
      "番号": 1,
      "支出先名": "モントリオール議定書多数国間基金・事務局",
      "法人番号": null,
      "業務概要": "開発途上国におけるHFC削減のための活動",
      "支出額": 24.0
    }
  ],
  "アウトカム": [
    {
      "成果目標": "条約の専門家パネルに日本政府から推薦する邦人専門家を1名以上確保する。",
      "成果指標": "条約の専門家パネルの委員である、日本政府から推薦した邦人専門家の数",
      "単位": "人",
      "目標値": null,
      "目標最終年度": null,
      "成果実績": [
        {
          "年度": 2017,
          "成果実績": null,
          "目標値": null
        },
        {
          "年度": 2018,
          "成果実績": null,
          "目標値": null
        },
        {
          "年度": 2019,
          "成果実績": 1.0,
          "目標値": 1.0
        }
      ]
    }
  ],
  "定量的な目標が設定できない理由": null,
  "アウトプット": [
    {
      "活動指標": "多数国間基金執行委員会の開催回数",
      "単位": "件",
      "活動実績": [
        {
          "年度": 2017,
          "活動実績": null,
          "当初見込み": null
        },
        {
          "年度": 2018,
          "活動実績": null,
          "当初見込み": null
        },
        {
          "年度": 2019,
          "活動実績": 2.0,
          "当初見込み": 2.0
        }
      ]
    }
  ],
  "関連する過去のレビューシート": []
}